[
  {
    "ID": "Leader_Finn",
    "Name": "!!Leader_Finn_NAME",
    "HPMod": "1",
    "LeaderAbility": "LDR_Draw_1",
    "APThreshold": "15",
    "ActionCard1": "Leader_Finn_01",
    "ActionCard2": "Leader_Finn_02",
    "ActionCard3": "Leader_Finn_03",
    "ActionCard4": "Leader_Finn_04",
    "ActionCard5": "Leader_Finn_05",
    "Prefab": "Finn",
    "VO": "Finn",
    "UseChair": "True",
    "ChairOffsetX": "0",
    "ChairOffsetY": "-1.5",
    "CharacterOffsetX": "0",
    "CharacterOffsetY": "3",
    "HeightAdjust": "2",
    "ThoughtBubbleHeightAdjust": "-90",
    "QuestPortraitTexture": "Finn_Battle_Image",
    "PortraitTexture": "Portrait_Finn_Hero",
    "VSScreenBackground": "Backdrop_Treehouse",
    "Playable": "True",
    "BuyCost": "2500",
    "CameraWinAnim": "Cam_Warrior_Win",
    "PIPTransformP1": "PIP_Finn_Player",
    "PIPTransformP2": "PIP_Finn_Opp",
    "CardRemoveAnimTime": "15",
    "CardPlayAnimTime": "23",
    "BigCardPlayAnimTime": "36",
    "Age": "!!Leader_Finn_AGE",
    "Height": "!!Leader_Finn_HEIGHT",
    "Weight": "!!Leader_Finn_WEIGHT",
    "Species": "!!Leader_Finn_SPECIES",
    "Quote": "!!Leader_Finn_QUOTE",
    "LeaderVFX": "Leader_Warrior_VFX",
    "SaleStartDate1": "ALWAYS"
  },
  {
    "ID": "Leader_FinnPajama",
    "Name": "Pajama Finn",
    "HPMod": "1",
    "LeaderAbility": "LDR_Draw_1",
    "APThreshold": "15",
    "ActionCard1": "Leader_Finn_01",
    "ActionCard2": "Leader_Finn_02",
    "ActionCard3": "Leader_Finn_03",
    "ActionCard4": "Leader_Finn_04",
    "ActionCard5": "Leader_Finn_05",
    "Prefab": "Finn_Pjama",
    "VO": "Finn",
    "UseChair": "True",
    "ChairOffsetX": "0",
    "ChairOffsetY": "-1.5",
    "CharacterOffsetX": "0",
    "CharacterOffsetY": "3",
    "HeightAdjust": "2",
    "ThoughtBubbleHeightAdjust": "-90",
    "QuestPortraitTexture": "Finn_Battle_Image",
    "PortraitTexture": "Portrait_FinnPajama_Hero",
    "VSScreenBackground": "Backdrop_Treehouse",
    "SkinOf": "Leader_Finn",
    "BuyableSkin": "True",
    "SkinBuyCost": "1500",
    "CameraWinAnim": "Cam_Warrior_Win",
    "PIPTransformP1": "PIP_Finn_Player",
    "PIPTransformP2": "PIP_Finn_Opp",
    "CardRemoveAnimTime": "15",
    "CardPlayAnimTime": "23",
    "BigCardPlayAnimTime": "36",
    "Age": "!!Leader_Finn_AGE",
    "Height": "!!Leader_Finn_HEIGHT",
    "Weight": "!!Leader_Finn_WEIGHT",
    "Species": "!!Leader_Finn_SPECIES",
    "Quote": "!!Leader_Finn_QUOTE",
    "LeaderVFX": "Leader_Warrior_VFX",
    "SaleStartDate1": "ALWAYS"
  },
  {
    "ID": "Leader_FinnDoctor",
    "Name": "Doctor Finn",
    "HPMod": "1",
    "LeaderAbility": "LDR_Draw_1",
    "APThreshold": "15",
    "ActionCard1": "Leader_Finn_01",
    "ActionCard2": "Leader_Finn_02",
    "ActionCard3": "Leader_Finn_03",
    "ActionCard4": "Leader_Finn_04",
    "ActionCard5": "Leader_Finn_05",
    "Prefab": "FinnDoctor",
    "VO": "Finn",
    "UseChair": "True",
    "ChairOffsetX": "0",
    "ChairOffsetY": "-1.5",
    "CharacterOffsetX": "0",
    "CharacterOffsetY": "3",
    "HeightAdjust": "2",
    "ThoughtBubbleHeightAdjust": "-90",
    "QuestPortraitTexture": "Finn_Battle_Image",
    "PortraitTexture": "Portrait_FinnDoctor_Hero",
    "VSScreenBackground": "Backdrop_Treehouse",
    "SkinOf": "Leader_Finn",
    "BuyableSkin": "True",
    "SkinBuyCost": "1500",
    "CameraWinAnim": "Cam_Warrior_Win",
    "PIPTransformP1": "PIP_Finn_Player",
    "PIPTransformP2": "PIP_Finn_Opp",
    "CardRemoveAnimTime": "15",
    "CardPlayAnimTime": "23",
    "BigCardPlayAnimTime": "36",
    "Age": "!!Leader_Finn_AGE",
    "Height": "!!Leader_Finn_HEIGHT",
    "Weight": "!!Leader_Finn_WEIGHT",
    "Species": "!!Leader_Finn_SPECIES",
    "Quote": "!!Leader_Finn_QUOTE",
    "LeaderVFX": "Leader_Warrior_VFX",
    "SaleStartDate1": "ALWAYS"
  },
  {
    "ID": "Leader_FinnDavey",
    "Name": "!!Leader_FinnDavey_NAME",
    "HPMod": "1",
    "LeaderAbility": "LDR_Draw_1",
    "APThreshold": "15",
    "ActionCard1": "Leader_Finn_01",
    "ActionCard2": "Leader_Finn_02",
    "ActionCard3": "Leader_Finn_03",
    "ActionCard4": "Leader_Finn_04",
    "ActionCard5": "Leader_Finn_05",
    "Prefab": "FinnDavey",
    "VO": "Finn",
    "UseChair": "True",
    "ChairOffsetX": "0",
    "ChairOffsetY": "-1.5",
    "CharacterOffsetX": "0",
    "CharacterOffsetY": "3",
    "HeightAdjust": "2",
    "ThoughtBubbleHeightAdjust": "-90",
    "QuestPortraitTexture": "Finn_Battle_Image",
    "PortraitTexture": "Portrait_FinnDavey_Hero",
    "VSScreenBackground": "Backdrop_Treehouse",
    "SkinOf": "Leader_Finn",
    "BuyableSkin": "True",
    "SkinBuyCost": "1000",
    "CameraWinAnim": "Cam_Warrior_Win",
    "PIPTransformP1": "PIP_Finn_Player",
    "PIPTransformP2": "PIP_Finn_Opp",
    "CardRemoveAnimTime": "15",
    "CardPlayAnimTime": "23",
    "BigCardPlayAnimTime": "36",
    "Age": "!!Leader_FinnDavey_AGE",
    "Height": "!!Leader_FinnDavey_HEIGHT",
    "Weight": "!!Leader_FinnDavey_WEIGHT",
    "Species": "!!Leader_FinnDavey_SPECIES",
    "Quote": "!!Leader_FinnDavey_QUOTE",
    "LeaderVFX": "Leader_Warrior_VFX",
    "SaleStartDate1": "ALWAYS"
  },
  {
    "ID": "Leader_FinnHoliday",
    "Name": "!!Leader_FinnHoliday_NAME",
    "HPMod": "1",
    "LeaderAbility": "LDR_Draw_1",
    "APThreshold": "15",
    "ActionCard1": "Leader_Finn_01",
    "ActionCard2": "Leader_Finn_02",
    "ActionCard3": "Leader_Finn_03",
    "ActionCard4": "Leader_Finn_04",
    "ActionCard5": "Leader_Finn_05",
    "Prefab": "Finn_Sweater",
    "VO": "Finn",
    "UseChair": "True",
    "ChairOffsetX": "0",
    "ChairOffsetY": "-1.5",
    "CharacterOffsetX": "0",
    "CharacterOffsetY": "3",
    "HeightAdjust": "2",
    "ThoughtBubbleHeightAdjust": "-90",
    "QuestPortraitTexture": "FinnSweater_Battle_Image",
    "PortraitTexture": "Portrait_SweaterFinn_Hero",
    "VSScreenBackground": "Backdrop_Treehouse",
    "SkinOf": "Leader_Finn",
    "BuyableSkin": "True",
    "SkinBuyCost": "1000",
    "CameraWinAnim": "Cam_Warrior_Win",
    "PIPTransformP1": "PIP_Finn_Player",
    "PIPTransformP2": "PIP_Finn_Opp",
    "CardRemoveAnimTime": "15",
    "CardPlayAnimTime": "23",
    "BigCardPlayAnimTime": "36",
    "Age": "!!Leader_FinnHoliday_AGE",
    "Height": "!!Leader_FinnHoliday_HEIGHT",
    "Weight": "!!Leader_FinnHoliday_WEIGHT",
    "Species": "!!Leader_FinnHoliday_SPECIES",
    "Quote": "!!Leader_FinnHoliday_QUOTE",
    "LeaderVFX": "Leader_Warrior_VFX",
    "SaleStartDate1": "ALWAYS"
  },
  {
    "ID": "Leader_Finn_GHO",
    "Name": "!!Leader_Finn_GHO_NAME",
    "HPMod": "1",
    "LeaderAbility": "LDR_Draw_1",
    "APThreshold": "15",
    "ActionCard1": "Leader_Finn_01",
    "ActionCard2": "Leader_Finn_02",
    "ActionCard3": "Leader_Finn_03",
    "ActionCard4": "Leader_Finn_04",
    "ActionCard5": "Leader_Finn_05",
    "Prefab": "Finn_Hal",
    "VO": "Finn",
    "UseChair": "True",
    "ChairOffsetX": "0",
    "ChairOffsetY": "-1.5",
    "CharacterOffsetX": "0",
    "CharacterOffsetY": "3",
    "HeightAdjust": "2",
    "ThoughtBubbleHeightAdjust": "-90",
    "QuestPortraitTexture": "Finn_Battle_Image_Hal",
    "PortraitTexture": "Portrait_Finn_Hero_Hal",
    "VSScreenBackground": "Backdrop_Cemetery",
    "SkinOf": "Leader_Finn",
    "BuyableSkin": "False",
    "SkinBuyCost": "2000",
    "CameraWinAnim": "Cam_Warrior_Win",
    "PIPTransformP1": "PIP_Finn_Player",
    "PIPTransformP2": "PIP_Finn_Opp",
    "CardRemoveAnimTime": "15",
    "CardPlayAnimTime": "23",
    "BigCardPlayAnimTime": "36",
    "Age": "!!Leader_Finn_GHO_AGE",
    "Height": "!!Leader_Finn_GHO_HEIGHT",
    "Weight": "!!Leader_Finn_GHO_WEIGHT",
    "Species": "!!Leader_Finn_GHO_SPECIES",
    "Quote": "!!Leader_Finn_GHO_QUOTE",
    "LeaderVFX": "Leader_Warrior_VFX",
    "SaleStartDate1": "ALWAYS"
  },
  {
    "ID": "Leader_Jake",
    "Name": "!!Leader_Jake_NAME",
    "HPMod": "1",
    "LeaderAbility": "LDR_Draw_1",
    "APThreshold": "15",
    "ActionCard1": "Leader_Jake_01",
    "ActionCard2": "Leader_Jake_02",
    "ActionCard3": "Leader_Jake_03",
    "ActionCard4": "Leader_Jake_04",
    "ActionCard5": "Leader_Jake_05",
    "Prefab": "Jake",
    "VO": "Jake",
    "UseChair": "True",
    "ChairOffsetX": "0",
    "ChairOffsetY": "3",
    "CharacterOffsetX": "0",
    "CharacterOffsetY": "3",
    "HeightAdjust": "-7",
    "ThoughtBubbleHeightAdjust": "-110",
    "QuestPortraitTexture": "Jake_Battle_Image",
    "PortraitTexture": "Portrait_Jake_Hero",
    "VSScreenBackground": "Backdrop_Treehouse2",
    "Playable": "True",
    "BuyCost": "-1",
    "CameraWinAnim": "Cam_Thief_Win",
    "PIPTransformP1": "PIP_Jake_Player",
    "PIPTransformP2": "PIP_Jake_Opp",
    "CardRemoveAnimTime": "15",
    "CardPlayAnimTime": "23",
    "BigCardPlayAnimTime": "36",
    "Age": "!!Leader_Jake_AGE",
    "Height": "!!Leader_Jake_HEIGHT",
    "Weight": "!!Leader_Jake_WEIGHT",
    "Species": "!!Leader_Jake_SPECIES",
    "Quote": "!!Leader_Jake_QUOTE",
    "LeaderVFX": "Leader_Thief_VFX",
    "SaleStartDate1": "ALWAYS"
  },
  {
    "ID": "Leader_JakeKing",
    "Name": "!!Leader_JakeKing_NAME",
    "HPMod": "1",
    "LeaderAbility": "LDR_Draw_1",
    "APThreshold": "15",
    "ActionCard1": "Leader_Jake_01",
    "ActionCard2": "Leader_Jake_02",
    "ActionCard3": "Leader_Jake_03",
    "ActionCard4": "Leader_Jake_04",
    "ActionCard5": "Leader_Jake_05",
    "Prefab": "JakeKing",
    "VO": "Jake",
    "UseChair": "True",
    "ChairOffsetX": "0",
    "ChairOffsetY": "3",
    "CharacterOffsetX": "0",
    "CharacterOffsetY": "3",
    "HeightAdjust": "-7",
    "ThoughtBubbleHeightAdjust": "-110",
    "QuestPortraitTexture": "Jake_Battle_Image",
    "PortraitTexture": "Portrait_JakeKing_Hero",
    "VSScreenBackground": "Backdrop_Treehouse2",
    "SkinOf": "Leader_Jake",
    "BuyableSkin": "True",
    "SkinBuyCost": "1000",
    "CameraWinAnim": "Cam_Thief_Win",
    "PIPTransformP1": "PIP_Jake_Player",
    "PIPTransformP2": "PIP_Jake_Opp",
    "CardRemoveAnimTime": "15",
    "CardPlayAnimTime": "23",
    "BigCardPlayAnimTime": "36",
    "Age": "!!Leader_JakeKing_AGE",
    "Height": "!!Leader_JakeKing_HEIGHT",
    "Weight": "!!Leader_JakeKing_WEIGHT",
    "Species": "!!Leader_JakeKing_SPECIES",
    "Quote": "!!Leader_JakeKing_QUOTE",
    "LeaderVFX": "Leader_Thief_VFX",
    "SaleStartDate1": "ALWAYS"
  },
  {
    "ID": "Leader_JakeHoliday",
    "Name": "!!Leader_JakeHoliday_NAME",
    "HPMod": "1",
    "LeaderAbility": "LDR_Draw_1",
    "APThreshold": "15",
    "ActionCard1": "Leader_Jake_01",
    "ActionCard2": "Leader_Jake_02",
    "ActionCard3": "Leader_Jake_03",
    "ActionCard4": "Leader_Jake_04",
    "ActionCard5": "Leader_Jake_05",
    "Prefab": "Jake_Sweater",
    "VO": "Jake",
    "UseChair": "True",
    "ChairOffsetX": "0",
    "ChairOffsetY": "3",
    "CharacterOffsetX": "0",
    "CharacterOffsetY": "3",
    "HeightAdjust": "-7",
    "ThoughtBubbleHeightAdjust": "-110",
    "QuestPortraitTexture": "JakeSweater_Battle_Image",
    "PortraitTexture": "Portrait_SweaterJake_Hero",
    "VSScreenBackground": "Backdrop_Treehouse2",
    "SkinOf": "Leader_Jake",
    "BuyableSkin": "True",
    "SkinBuyCost": "1000",
    "CameraWinAnim": "Cam_Thief_Win",
    "PIPTransformP1": "PIP_Jake_Player",
    "PIPTransformP2": "PIP_Jake_Opp",
    "CardRemoveAnimTime": "15",
    "CardPlayAnimTime": "23",
    "BigCardPlayAnimTime": "36",
    "Age": "!!Leader_JakeHoliday_AGE",
    "Height": "!!Leader_JakeHoliday_HEIGHT",
    "Weight": "!!Leader_JakeHoliday_WEIGHT",
    "Species": "!!Leader_JakeHoliday_SPECIES",
    "Quote": "!!Leader_JakeHoliday_QUOTE",
    "LeaderVFX": "Leader_Thief_VFX",
    "SaleStartDate1": "ALWAYS"
  },
  {
    "ID": "Leader_Jake_GHO",
    "Name": "!!Leader_Jake_GHO_NAME",
    "HPMod": "1",
    "LeaderAbility": "LDR_Draw_1",
    "APThreshold": "15",
    "ActionCard1": "Leader_Jake_01",
    "ActionCard2": "Leader_Jake_02",
    "ActionCard3": "Leader_Jake_03",
    "ActionCard4": "Leader_Jake_04",
    "ActionCard5": "Leader_Jake_05",
    "Prefab": "Jake_Hal",
    "VO": "Jake",
    "UseChair": "True",
    "ChairOffsetX": "0",
    "ChairOffsetY": "3",
    "CharacterOffsetX": "0",
    "CharacterOffsetY": "3",
    "HeightAdjust": "-7",
    "ThoughtBubbleHeightAdjust": "-110",
    "QuestPortraitTexture": "Jake_Battle_Image_Hal",
    "PortraitTexture": "Portrait_Jake_Hero_Hal",
    "VSScreenBackground": "Backdrop_Cemetery",
    "SkinOf": "Leader_Jake",
    "BuyableSkin": "False",
    "SkinBuyCost": "2000",
    "CameraWinAnim": "Cam_Thief_Win",
    "PIPTransformP1": "PIP_Jake_Player",
    "PIPTransformP2": "PIP_Jake_Opp",
    "CardRemoveAnimTime": "15",
    "CardPlayAnimTime": "23",
    "BigCardPlayAnimTime": "36",
    "Age": "!!Leader_Jake_GHO_AGE",
    "Height": "!!Leader_Jake_GHO_HEIGHT",
    "Weight": "!!Leader_Jake_GHO_WEIGHT",
    "Species": "!!Leader_Jake_GHO_SPECIES",
    "Quote": "!!Leader_Jake_GHO_QUOTE",
    "LeaderVFX": "Leader_Thief_VFX",
    "SaleStartDate1": "ALWAYS"
  },
  {
    "ID": "Leader_JakeZombie",
    "Name": "Zombie Jake",
    "HPMod": "1",
    "LeaderAbility": "LDR_Draw_1",
    "APThreshold": "15",
    "ActionCard1": "Leader_Jake_01",
    "ActionCard2": "Leader_Jake_02",
    "ActionCard3": "Leader_Jake_03",
    "ActionCard4": "Leader_Jake_04",
    "ActionCard5": "Leader_Jake_05",
    "Prefab": "Jake_Zombie",
    "VO": "Jake",
    "UseChair": "True",
    "ChairOffsetX": "0",
    "ChairOffsetY": "3",
    "CharacterOffsetX": "0",
    "CharacterOffsetY": "3",
    "HeightAdjust": "-7",
    "ThoughtBubbleHeightAdjust": "-110",
    "QuestPortraitTexture": "Jake_Battle_Image",
    "PortraitTexture": "Portrait_JakeZombie_Hero",
    "VSScreenBackground": "Backdrop_Cemetery",
    "SkinOf": "Leader_Jake",
    "BuyableSkin": "False",
    "SkinBuyCost": "1000",
    "CameraWinAnim": "Cam_Thief_Win",
    "PIPTransformP1": "PIP_Jake_Player",
    "PIPTransformP2": "PIP_Jake_Opp",
    "CardRemoveAnimTime": "15",
    "CardPlayAnimTime": "23",
    "BigCardPlayAnimTime": "36",
    "Age": "!!Leader_JakeKing_AGE",
    "Height": "!!Leader_JakeKing_HEIGHT",
    "Weight": "!!Leader_JakeKing_WEIGHT",
    "Species": "!!Leader_JakeKing_SPECIES",
    "Quote": "!!Leader_JakeKing_QUOTE",
    "LeaderVFX": "Leader_Thief_VFX",
    "SaleStartDate1": "ALWAYS"
  },
  {
    "ID": "Leader_FlamePrincess",
    "Name": "!!Leader_FlamePrincess_NAME",
    "HPMod": "1",
    "LeaderAbility": "LDR_Draw_1",
    "APThreshold": "15",
    "ActionCard1": "Leader_FlamePrincess_01",
    "ActionCard2": "Leader_FlamePrincess_02",
    "ActionCard3": "Leader_FlamePrincess_03",
    "ActionCard4": "Leader_FlamePrincess_04",
    "ActionCard5": "Leader_FlamePrincess_05",
    "Prefab": "FlamePrincess",
    "VO": "FlamePrincess",
    "UseChair": "True",
    "ChairOffsetX": "0",
    "ChairOffsetY": "-1.5",
    "CharacterOffsetX": "0",
    "CharacterOffsetY": "3",
    "HeightAdjust": "0",
    "ThoughtBubbleHeightAdjust": "-90",
    "QuestPortraitTexture": "FlamePrincess_Battle_Image",
    "PortraitTexture": "Portrait_FlamePrincess_Hero",
    "VSScreenBackground": "Backdrop_FireKingdom",
    "Playable": "True",
    "BuyCost": "1500",
    "CameraWinAnim": "Cam_Gork_Win",
    "PIPTransformP1": "PIP_FlamePrincess_Player",
    "PIPTransformP2": "PIP_FlamePrincess_Opp",
    "CardRemoveAnimTime": "15",
    "CardPlayAnimTime": "23",
    "BigCardPlayAnimTime": "36",
    "Age": "!!Leader_FlamePrincess_AGE",
    "Height": "!!Leader_FlamePrincess_HEIGHT",
    "Weight": "!!Leader_FlamePrincess_WEIGHT",
    "Species": "!!Leader_FlamePrincess_SPECIES",
    "Quote": "!!Leader_FlamePrincess_QUOTE",
    "LeaderVFX": "Leader_Gork_VFX",
    "SaleStartDate1": "ALWAYS"
  },
  {
    "ID": "Leader_BlueFlamePrincess",
    "Name": "!!Leader_BlueFlamePrincess_NAME",
    "HPMod": "1",
    "LeaderAbility": "LDR_Draw_1",
    "APThreshold": "15",
    "ActionCard1": "Leader_FlamePrincess_01",
    "ActionCard2": "Leader_FlamePrincess_02",
    "ActionCard3": "Leader_FlamePrincess_03",
    "ActionCard4": "Leader_FlamePrincess_04",
    "ActionCard5": "Leader_FlamePrincess_05",
    "Prefab": "BlueFlamePrincess",
    "VO": "FlamePrincess",
    "UseChair": "True",
    "ChairOffsetX": "0",
    "ChairOffsetY": "-1.5",
    "CharacterOffsetX": "0",
    "CharacterOffsetY": "3",
    "HeightAdjust": "0",
    "ThoughtBubbleHeightAdjust": "-90",
    "QuestPortraitTexture": "FlamePrincess_Battle_Image",
    "PortraitTexture": "Portrait_BlueFlamePrincess_Hero",
    "VSScreenBackground": "Backdrop_FireKingdom",
    "SkinOf": "Leader_FlamePrincess",
    "BuyableSkin": "True",
    "SkinBuyCost": "1000",
    "CameraWinAnim": "Cam_Gork_Win",
    "PIPTransformP1": "PIP_FlamePrincess_Player",
    "PIPTransformP2": "PIP_FlamePrincess_Opp",
    "CardRemoveAnimTime": "15",
    "CardPlayAnimTime": "23",
    "BigCardPlayAnimTime": "36",
    "Age": "!!Leader_BlueFlamePrincess_AGE",
    "Height": "!!Leader_BlueFlamePrincess_HEIGHT",
    "Weight": "!!Leader_BlueFlamePrincess_WEIGHT",
    "Species": "!!Leader_BlueFlamePrincess_SPECIES",
    "Quote": "!!Leader_BlueFlamePrincess_QUOTE",
    "LeaderVFX": "Leader_Gork_VFX",
    "SaleStartDate1": "ALWAYS"
  },
  {
    "ID": "Leader_FlamePrincess_GHO",
    "Name": "!!Leader_FlamePrincess_GHO_NAME",
    "HPMod": "1",
    "LeaderAbility": "LDR_Draw_1",
    "APThreshold": "15",
    "ActionCard1": "Leader_FlamePrincess_01",
    "ActionCard2": "Leader_FlamePrincess_02",
    "ActionCard3": "Leader_FlamePrincess_03",
    "ActionCard4": "Leader_FlamePrincess_04",
    "ActionCard5": "Leader_FlamePrincess_05",
    "Prefab": "FlamePrincess_Hal",
    "VO": "FlamePrincess",
    "UseChair": "True",
    "ChairOffsetX": "0",
    "ChairOffsetY": "-1.5",
    "CharacterOffsetX": "0",
    "CharacterOffsetY": "3",
    "HeightAdjust": "0",
    "ThoughtBubbleHeightAdjust": "-90",
    "QuestPortraitTexture": "FlamePrincess_Battle_Image_Hal",
    "PortraitTexture": "Portrait_FlamePrincess_Hero_Hal",
    "VSScreenBackground": "Backdrop_Cemetery",
    "SkinOf": "Leader_FlamePrincess",
    "BuyableSkin": "False",
    "SkinBuyCost": "2000",
    "CameraWinAnim": "Cam_Gork_Win",
    "PIPTransformP1": "PIP_FlamePrincess_Player",
    "PIPTransformP2": "PIP_FlamePrincess_Opp",
    "CardRemoveAnimTime": "15",
    "CardPlayAnimTime": "23",
    "BigCardPlayAnimTime": "36",
    "Age": "!!Leader_FlamePrincess_GHO_AGE",
    "Height": "!!Leader_FlamePrincess_GHO_HEIGHT",
    "Weight": "!!Leader_FlamePrincess_GHO_WEIGHT",
    "Species": "!!Leader_FlamePrincess_GHO_SPECIES",
    "Quote": "!!Leader_FlamePrincess_GHO_QUOTE",
    "LeaderVFX": "Leader_Gork_VFX",
    "SaleStartDate1": "ALWAYS"
  },
  {
    "ID": "Leader_IceKing",
    "Name": "!!Leader_IceKing_NAME",
    "HPMod": "1",
    "LeaderAbility": "LDR_Draw_1",
    "APThreshold": "15",
    "ActionCard1": "Leader_IceKing_01",
    "ActionCard2": "Leader_IceKing_02",
    "ActionCard3": "Leader_IceKing_03",
    "ActionCard4": "Leader_IceKing_04",
    "ActionCard5": "Leader_IceKing_05",
    "Prefab": "IceKing",
    "VO": "IceKing",
    "UseChair": "False",
    "ChairOffsetX": "0",
    "ChairOffsetY": "0",
    "CharacterOffsetX": "0",
    "CharacterOffsetY": "3",
    "HeightAdjust": "10",
    "ThoughtBubbleHeightAdjust": "0",
    "QuestPortraitTexture": "IceKing_Battle_Image",
    "PortraitTexture": "Portrait_IceKing_Hero",
    "VSScreenBackground": "Backdrop_IceCave",
    "Playable": "True",
    "BuyCost": "2800",
    "CameraWinAnim": "Cam_Druid_Win",
    "PIPTransformP1": "PIP_IceKing_Player",
    "PIPTransformP2": "PIP_IceKing_Opp",
    "CardRemoveAnimTime": "15",
    "CardPlayAnimTime": "23",
    "BigCardPlayAnimTime": "36",
    "Age": "!!Leader_IceKing_AGE",
    "Height": "!!Leader_IceKing_HEIGHT",
    "Weight": "!!Leader_IceKing_WEIGHT",
    "Species": "!!Leader_IceKing_SPECIES",
    "Quote": "!!Leader_IceKing_QUOTE",
    "LeaderVFX": "Leader_Druid_VFX",
    "SaleStartDate1": "ALWAYS"
  },
  {
    "ID": "Leader_IceKing_Pajama",
    "Name": "Pajama Ice King",
    "HPMod": "1",
    "LeaderAbility": "LDR_Draw_1",
    "APThreshold": "15",
    "ActionCard1": "Leader_IceKing_01",
    "ActionCard2": "Leader_IceKing_02",
    "ActionCard3": "Leader_IceKing_03",
    "ActionCard4": "Leader_IceKing_04",
    "ActionCard5": "Leader_IceKing_05",
    "Prefab": "IceKing_Pjama",
    "VO": "IceKing",
    "UseChair": "False",
    "ChairOffsetX": "0",
    "ChairOffsetY": "0",
    "CharacterOffsetX": "0",
    "CharacterOffsetY": "3",
    "HeightAdjust": "10",
    "ThoughtBubbleHeightAdjust": "0",
    "QuestPortraitTexture": "IceKingSweater_Battle_Image",
    "PortraitTexture": "Portrait_IceKingPajama_Hero",
    "VSScreenBackground": "Backdrop_IceCave",
    "SkinOf": "Leader_IceKing",
    "BuyableSkin": "True",
    "SkinBuyCost": "2000",
    "CameraWinAnim": "Cam_Druid_Win",
    "PIPTransformP1": "PIP_IceKing_Player",
    "PIPTransformP2": "PIP_IceKing_Opp",
    "CardRemoveAnimTime": "15",
    "CardPlayAnimTime": "23",
    "BigCardPlayAnimTime": "36",
    "Age": "!!Leader_IceKing_Holiday_AGE",
    "Height": "!!Leader_IceKing_Holiday_HEIGHT",
    "Weight": "!!Leader_IceKing_Holiday_WEIGHT",
    "Species": "!!Leader_IceKing_Holiday_SPECIES",
    "Quote": "!!Leader_IceKing_Holiday_QUOTE",
    "LeaderVFX": "Leader_Druid_VFX",
    "SaleStartDate1": "ALWAYS"
  },
  {
    "ID": "Leader_IceKing_DateNight",
    "Name": "!!Leader_IceKing_DateNight_NAME",
    "HPMod": "1",
    "LeaderAbility": "LDR_Draw_1",
    "APThreshold": "15",
    "ActionCard1": "Leader_IceKing_01",
    "ActionCard2": "Leader_IceKing_02",
    "ActionCard3": "Leader_IceKing_03",
    "ActionCard4": "Leader_IceKing_04",
    "ActionCard5": "Leader_IceKing_05",
    "Prefab": "IceKing_DateNight",
    "VO": "IceKing",
    "UseChair": "False",
    "ChairOffsetX": "0",
    "ChairOffsetY": "0",
    "CharacterOffsetX": "0",
    "CharacterOffsetY": "3",
    "HeightAdjust": "10",
    "ThoughtBubbleHeightAdjust": "0",
    "QuestPortraitTexture": "IceKing_Battle_Image",
    "PortraitTexture": "Portrait_IceKing_DateNight_Hero",
    "VSScreenBackground": "Backdrop_IceCave",
    "SkinOf": "Leader_IceKing",
    "SkinBuyCost": "1000",
    "CameraWinAnim": "Cam_Druid_Win",
    "PIPTransformP1": "PIP_IceKing_Player",
    "PIPTransformP2": "PIP_IceKing_Opp",
    "CardRemoveAnimTime": "15",
    "CardPlayAnimTime": "23",
    "BigCardPlayAnimTime": "36",
    "Age": "!!Leader_IceKing_DateNight_AGE",
    "Height": "!!Leader_IceKing_DateNight_HEIGHT",
    "Weight": "!!Leader_IceKing_DateNight_WEIGHT",
    "Species": "!!Leader_IceKing_DateNight_SPECIES",
    "Quote": "!!Leader_IceKing_DateNight_QUOTE",
    "LeaderVFX": "Leader_Druid_VFX",
    "SaleStartDate1": "ALWAYS"
  },
  {
    "ID": "Leader_IceKing_Holiday",
    "Name": "!!Leader_IceKing_Holiday_NAME",
    "HPMod": "1",
    "LeaderAbility": "LDR_Draw_1",
    "APThreshold": "15",
    "ActionCard1": "Leader_IceKing_01",
    "ActionCard2": "Leader_IceKing_02",
    "ActionCard3": "Leader_IceKing_03",
    "ActionCard4": "Leader_IceKing_04",
    "ActionCard5": "Leader_IceKing_05",
    "Prefab": "IceKing_Sweater",
    "VO": "IceKing",
    "UseChair": "False",
    "ChairOffsetX": "0",
    "ChairOffsetY": "0",
    "CharacterOffsetX": "0",
    "CharacterOffsetY": "3",
    "HeightAdjust": "10",
    "ThoughtBubbleHeightAdjust": "0",
    "QuestPortraitTexture": "IceKingSweater_Battle_Image",
    "PortraitTexture": "Portrait_SweaterIceKing_Hero",
    "VSScreenBackground": "Backdrop_IceCave",
    "SkinOf": "Leader_IceKing",
    "BuyableSkin": "True",
    "SkinBuyCost": "1000",
    "CameraWinAnim": "Cam_Druid_Win",
    "PIPTransformP1": "PIP_IceKing_Player",
    "PIPTransformP2": "PIP_IceKing_Opp",
    "CardRemoveAnimTime": "15",
    "CardPlayAnimTime": "23",
    "BigCardPlayAnimTime": "36",
    "Age": "!!Leader_IceKing_Holiday_AGE",
    "Height": "!!Leader_IceKing_Holiday_HEIGHT",
    "Weight": "!!Leader_IceKing_Holiday_WEIGHT",
    "Species": "!!Leader_IceKing_Holiday_SPECIES",
    "Quote": "!!Leader_IceKing_Holiday_QUOTE",
    "LeaderVFX": "Leader_Druid_VFX",
    "SaleStartDate1": "ALWAYS"
  },
  {
    "ID": "Leader_IceKing_GHO",
    "Name": "!!Leader_IceKing_GHO_NAME",
    "HPMod": "1",
    "LeaderAbility": "LDR_Draw_1",
    "APThreshold": "15",
    "ActionCard1": "Leader_IceKing_01",
    "ActionCard2": "Leader_IceKing_02",
    "ActionCard3": "Leader_IceKing_03",
    "ActionCard4": "Leader_IceKing_04",
    "ActionCard5": "Leader_IceKing_05",
    "Prefab": "IceKing_Hal",
    "VO": "IceKing",
    "UseChair": "False",
    "ChairOffsetX": "0",
    "ChairOffsetY": "0",
    "CharacterOffsetX": "0",
    "CharacterOffsetY": "3",
    "HeightAdjust": "10",
    "ThoughtBubbleHeightAdjust": "0",
    "QuestPortraitTexture": "IceKing_Battle_Image_Hal",
    "PortraitTexture": "Portrait_IceKing_Hero_Hal",
    "VSScreenBackground": "Backdrop_Cemetery",
    "SkinOf": "Leader_IceKing",
    "BuyableSkin": "False",
    "SkinBuyCost": "2000",
    "CameraWinAnim": "Cam_Druid_Win",
    "PIPTransformP1": "PIP_IceKing_Player",
    "PIPTransformP2": "PIP_IceKing_Opp",
    "CardRemoveAnimTime": "15",
    "CardPlayAnimTime": "23",
    "BigCardPlayAnimTime": "36",
    "Age": "!!Leader_IceKing_GHO_AGE",
    "Height": "!!Leader_IceKing_GHO_HEIGHT",
    "Weight": "!!Leader_IceKing_GHO_WEIGHT",
    "Species": "!!Leader_IceKing_GHO_SPECIES",
    "Quote": "!!Leader_IceKing_GHO_QUOTE",
    "LeaderVFX": "Leader_Druid_VFX",
    "SaleStartDate1": "ALWAYS"
  },
  {
    "ID": "Leader_LumpySpacePrincess",
    "Name": "!!Leader_LumpySpacePrincess_NAME",
    "HPMod": "1",
    "LeaderAbility": "LDR_Draw_1",
    "APThreshold": "15",
    "ActionCard1": "Leader_LumpySpacePrincess_01",
    "ActionCard2": "Leader_LumpySpacePrincess_02",
    "ActionCard3": "Leader_LumpySpacePrincess_03",
    "ActionCard4": "Leader_LumpySpacePrincess_04",
    "ActionCard5": "Leader_LumpySpacePrincess_05",
    "Prefab": "LumpySpacePrincess",
    "VO": "LumpySpacePrincess",
    "UseChair": "False",
    "ChairOffsetX": "0",
    "ChairOffsetY": "0",
    "CharacterOffsetX": "0",
    "CharacterOffsetY": "3",
    "HeightAdjust": "0",
    "ThoughtBubbleHeightAdjust": "-50",
    "QuestPortraitTexture": "LSP_Battle_Image",
    "PortraitTexture": "Portrait_Lumpy_Hero",
    "VSScreenBackground": "Backdrop_LumpySpace",
    "Playable": "True",
    "BuyCost": "2000",
    "CameraWinAnim": "Cam_Medusa_Win",
    "PIPTransformP1": "PIP_LumpySpacePrincess_Player",
    "PIPTransformP2": "PIP_LumpySpacePrincess_Opp",
    "CardRemoveAnimTime": "15",
    "CardPlayAnimTime": "23",
    "BigCardPlayAnimTime": "36",
    "Age": "!!Leader_LumpySpacePrincess_AGE",
    "Height": "!!Leader_LumpySpacePrincess_HEIGHT",
    "Weight": "!!Leader_LumpySpacePrincess_WEIGHT",
    "Species": "!!Leader_LumpySpacePrincess_SPECIES",
    "Quote": "!!Leader_LumpySpacePrincess_QUOTE",
    "LeaderVFX": "Leader_Medusa_VFX",
    "SaleStartDate1": "ALWAYS"
  },
  {
    "ID": "Leader_LumpySpacePrincess_Masquerade",
    "Name": "!!Leader_LumpySpacePrincess_Masquerade_NAME",
    "HPMod": "1",
    "LeaderAbility": "LDR_Draw_1",
    "APThreshold": "15",
    "ActionCard1": "Leader_LumpySpacePrincess_01",
    "ActionCard2": "Leader_LumpySpacePrincess_02",
    "ActionCard3": "Leader_LumpySpacePrincess_03",
    "ActionCard4": "Leader_LumpySpacePrincess_04",
    "ActionCard5": "Leader_LumpySpacePrincess_05",
    "Prefab": "LumpySpacePrincess_Masquerade",
    "VO": "LumpySpacePrincess",
    "UseChair": "False",
    "ChairOffsetX": "0",
    "ChairOffsetY": "0",
    "CharacterOffsetX": "0",
    "CharacterOffsetY": "3",
    "HeightAdjust": "0",
    "ThoughtBubbleHeightAdjust": "-50",
    "QuestPortraitTexture": "LSP_Battle_Image",
    "PortraitTexture": "Portrait_LumpySpacePrincess_Masquerade",
    "VSScreenBackground": "Backdrop_LumpySpace",
    "SkinOf": "Leader_LumpySpacePrincess",
    "BuyableSkin": "True",
    "SkinBuyCost": "1000",
    "CameraWinAnim": "Cam_Medusa_Win",
    "PIPTransformP1": "PIP_LumpySpacePrincess_Player",
    "PIPTransformP2": "PIP_LumpySpacePrincess_Opp",
    "CardRemoveAnimTime": "15",
    "CardPlayAnimTime": "23",
    "BigCardPlayAnimTime": "36",
    "Age": "!!Leader_LumpySpacePrincess_Masquerade_AGE",
    "Height": "!!Leader_LumpySpacePrincess_Masquerade_HEIGHT",
    "Weight": "!!Leader_LumpySpacePrincess_Masquerade_WEIGHT",
    "Species": "!!Leader_LumpySpacePrincess_Masquerade_SPECIES",
    "Quote": "!!Leader_LumpySpacePrincess_Masquerade_QUOTE",
    "LeaderVFX": "Leader_Medusa_VFX",
    "SaleStartDate1": "ALWAYS"
  },
  {
    "ID": "Leader_LumpySpacePrincess_Holiday",
    "Name": "!!Leader_LumpySpacePrincess_Holiday_NAME",
    "HPMod": "1",
    "LeaderAbility": "LDR_Draw_1",
    "APThreshold": "15",
    "ActionCard1": "Leader_LumpySpacePrincess_01",
    "ActionCard2": "Leader_LumpySpacePrincess_02",
    "ActionCard3": "Leader_LumpySpacePrincess_03",
    "ActionCard4": "Leader_LumpySpacePrincess_04",
    "ActionCard5": "Leader_LumpySpacePrincess_05",
    "Prefab": "LumpySpacePrincess_Sweater",
    "VO": "LumpySpacePrincess",
    "UseChair": "False",
    "ChairOffsetX": "0",
    "ChairOffsetY": "0",
    "CharacterOffsetX": "0",
    "CharacterOffsetY": "3",
    "HeightAdjust": "0",
    "ThoughtBubbleHeightAdjust": "-50",
    "QuestPortraitTexture": "LSPSweater_Battle_Image",
    "PortraitTexture": "Portrait_SweaterLumpy_Hero",
    "VSScreenBackground": "Backdrop_LumpySpace",
    "SkinOf": "Leader_LumpySpacePrincess",
    "BuyableSkin": "True",
    "SkinBuyCost": "1000",
    "CameraWinAnim": "Cam_Medusa_Win",
    "PIPTransformP1": "PIP_LumpySpacePrincess_Player",
    "PIPTransformP2": "PIP_LumpySpacePrincess_Opp",
    "CardRemoveAnimTime": "15",
    "CardPlayAnimTime": "23",
    "BigCardPlayAnimTime": "36",
    "Age": "!!Leader_LumpySpacePrincess_Holiday_AGE",
    "Height": "!!Leader_LumpySpacePrincess_Holiday_HEIGHT",
    "Weight": "!!Leader_LumpySpacePrincess_Holiday_WEIGHT",
    "Species": "!!Leader_LumpySpacePrincess_Holiday_SPECIES",
    "Quote": "!!Leader_LumpySpacePrincess_Holiday_QUOTE",
    "LeaderVFX": "Leader_Medusa_VFX",
    "SaleStartDate1": "ALWAYS"
  },
  {
    "ID": "Leader_LumpySpacePrincess_GHO",
    "Name": "!!Leader_LumpySpacePrincess_GHO_NAME",
    "HPMod": "1",
    "LeaderAbility": "LDR_Draw_1",
    "APThreshold": "15",
    "ActionCard1": "Leader_LumpySpacePrincess_01",
    "ActionCard2": "Leader_LumpySpacePrincess_02",
    "ActionCard3": "Leader_LumpySpacePrincess_03",
    "ActionCard4": "Leader_LumpySpacePrincess_04",
    "ActionCard5": "Leader_LumpySpacePrincess_05",
    "Prefab": "LumpySpacePrincess_Hal",
    "VO": "LumpySpacePrincess",
    "UseChair": "False",
    "ChairOffsetX": "0",
    "ChairOffsetY": "0",
    "CharacterOffsetX": "0",
    "CharacterOffsetY": "3",
    "HeightAdjust": "0",
    "ThoughtBubbleHeightAdjust": "-50",
    "QuestPortraitTexture": "LSP_Battle_Image_Hal",
    "PortraitTexture": "Portrait_Lumpy_Hero_Hal",
    "VSScreenBackground": "Backdrop_Cemetery",
    "SkinOf": "Leader_LumpySpacePrincess",
    "BuyableSkin": "False",
    "SkinBuyCost": "2000",
    "CameraWinAnim": "Cam_Medusa_Win",
    "PIPTransformP1": "PIP_LumpySpacePrincess_Player",
    "PIPTransformP2": "PIP_LumpySpacePrincess_Opp",
    "CardRemoveAnimTime": "15",
    "CardPlayAnimTime": "23",
    "BigCardPlayAnimTime": "36",
    "Age": "!!Leader_LumpySpacePrincess_GHO_AGE",
    "Height": "!!Leader_LumpySpacePrincess_GHO_HEIGHT",
    "Weight": "!!Leader_LumpySpacePrincess_GHO_WEIGHT",
    "Species": "!!Leader_LumpySpacePrincess_GHO_SPECIES",
    "Quote": "!!Leader_LumpySpacePrincess_GHO_QUOTE",
    "LeaderVFX": "Leader_Medusa_VFX",
    "SaleStartDate1": "ALWAYS"
  },
  {
    "ID": "Leader_Marceline",
    "Name": "!!Leader_Marceline_NAME",
    "HPMod": "1",
    "LeaderAbility": "LDR_Draw_1",
    "APThreshold": "15",
    "ActionCard1": "Leader_Marceline_01",
    "ActionCard2": "Leader_Marceline_02",
    "ActionCard3": "Leader_Marceline_03",
    "ActionCard4": "Leader_Marceline_04",
    "ActionCard5": "Leader_Marceline_05",
    "Prefab": "Marceline",
    "VO": "Marceline",
    "UseChair": "True",
    "ChairOffsetX": "0",
    "ChairOffsetY": "-1.5",
    "CharacterOffsetX": "0",
    "CharacterOffsetY": "3",
    "HeightAdjust": "0",
    "ThoughtBubbleHeightAdjust": "0",
    "QuestPortraitTexture": "Marceline_Battle_Image",
    "PortraitTexture": "Portrait_Marceline_Hero",
    "VSScreenBackground": "Backdrop_Marcelines",
    "Playable": "True",
    "BuyCost": "2700",
    "CameraWinAnim": "Cam_Dwarf_Win",
    "PIPTransformP1": "PIP_Marceline_Player",
    "PIPTransformP2": "PIP_Marceline_Opp",
    "CardRemoveAnimTime": "15",
    "CardPlayAnimTime": "23",
    "BigCardPlayAnimTime": "36",
    "Age": "!!Leader_Marceline_AGE",
    "Height": "!!Leader_Marceline_HEIGHT",
    "Weight": "!!Leader_Marceline_WEIGHT",
    "Species": "!!Leader_Marceline_SPECIES",
    "Quote": "!!Leader_Marceline_QUOTE",
    "LeaderVFX": "Leader_Dwarf_VFX",
    "SaleStartDate1": "ALWAYS"
  },
  {
    "ID": "Leader_Marceline_Stakes",
    "Name": "!!Leader_Marceline_Stakes_NAME",
    "HPMod": "1",
    "LeaderAbility": "LDR_Draw_1",
    "APThreshold": "15",
    "ActionCard1": "Leader_Marceline_01",
    "ActionCard2": "Leader_Marceline_02",
    "ActionCard3": "Leader_Marceline_03",
    "ActionCard4": "Leader_Marceline_04",
    "ActionCard5": "Leader_Marceline_05",
    "Prefab": "Marceline_Stakes",
    "VO": "Marceline",
    "UseChair": "True",
    "ChairOffsetX": "0",
    "ChairOffsetY": "-1.5",
    "CharacterOffsetX": "0",
    "CharacterOffsetY": "3",
    "HeightAdjust": "0",
    "ThoughtBubbleHeightAdjust": "0",
    "QuestPortraitTexture": "Marceline_Battle_Image",
    "PortraitTexture": "Portrait_Marceline_Stakes_Hero",
    "VSScreenBackground": "Backdrop_Marcelines",
    "SkinOf": "Leader_Marceline",
    "BuyableSkin": "True",
    "SkinBuyCost": "1000",
    "CameraWinAnim": "Cam_Dwarf_Win",
    "PIPTransformP1": "PIP_Marceline_Player",
    "PIPTransformP2": "PIP_Marceline_Opp",
    "CardRemoveAnimTime": "15",
    "CardPlayAnimTime": "23",
    "BigCardPlayAnimTime": "36",
    "Age": "!!Leader_Marceline_Stakes_AGE",
    "Height": "!!Leader_Marceline_Stakes_HEIGHT",
    "Weight": "!!Leader_Marceline_Stakes_WEIGHT",
    "Species": "!!Leader_Marceline_Stakes_SPECIES",
    "Quote": "!!Leader_Marceline_Stakes_QUOTE",
    "LeaderVFX": "Leader_Dwarf_VFX",
    "SaleStartDate1": "ALWAYS"
  },
  {
    "ID": "Leader_Marceline_GHO",
    "Name": "!!Leader_Marceline_GHO_NAME",
    "HPMod": "1",
    "LeaderAbility": "LDR_Draw_1",
    "APThreshold": "15",
    "ActionCard1": "Leader_Marceline_01",
    "ActionCard2": "Leader_Marceline_02",
    "ActionCard3": "Leader_Marceline_03",
    "ActionCard4": "Leader_Marceline_04",
    "ActionCard5": "Leader_Marceline_05",
    "Prefab": "Marceline_Hal",
    "VO": "Marceline",
    "UseChair": "True",
    "ChairOffsetX": "0",
    "ChairOffsetY": "-1.5",
    "CharacterOffsetX": "0",
    "CharacterOffsetY": "3",
    "HeightAdjust": "0",
    "ThoughtBubbleHeightAdjust": "0",
    "QuestPortraitTexture": "Marceline_Battle_Image_Hal",
    "PortraitTexture": "Portrait_Marceline_Hero_Hal",
    "VSScreenBackground": "Backdrop_Cemetery",
    "SkinOf": "Leader_Marceline",
    "BuyableSkin": "False",
    "SkinBuyCost": "2000",
    "CameraWinAnim": "Cam_Dwarf_Win",
    "PIPTransformP1": "PIP_Marceline_Player",
    "PIPTransformP2": "PIP_Marceline_Opp",
    "CardRemoveAnimTime": "15",
    "CardPlayAnimTime": "23",
    "BigCardPlayAnimTime": "36",
    "Age": "!!Leader_Marceline_GHO_AGE",
    "Height": "!!Leader_Marceline_GHO_HEIGHT",
    "Weight": "!!Leader_Marceline_GHO_WEIGHT",
    "Species": "!!Leader_Marceline_GHO_SPECIES",
    "Quote": "!!Leader_Marceline_GHO_QUOTE",
    "LeaderVFX": "Leader_Dwarf_VFX",
    "SaleStartDate1": "ALWAYS"
  },
  {
    "ID": "Leader_PrincessBubblegum",
    "Name": "!!Leader_PrincessBubblegum_NAME",
    "HPMod": "1",
    "LeaderAbility": "LDR_Draw_1",
    "APThreshold": "15",
    "ActionCard1": "Leader_PrincessBubblegum_01",
    "ActionCard2": "Leader_PrincessBubblegum_02",
    "ActionCard3": "Leader_PrincessBubblegum_03",
    "ActionCard4": "Leader_PrincessBubblegum_04",
    "ActionCard5": "Leader_PrincessBubblegum_05",
    "Prefab": "PrincessBubblegum",
    "VO": "PrincessBubblegum",
    "UseChair": "True",
    "ChairOffsetX": "0",
    "ChairOffsetY": "-1.5",
    "CharacterOffsetX": "0",
    "CharacterOffsetY": "3",
    "HeightAdjust": "10",
    "ThoughtBubbleHeightAdjust": "0",
    "QuestPortraitTexture": "PBG_Battle_Image",
    "PortraitTexture": "Portrait_Princess_Hero",
    "VSScreenBackground": "Backdrop_CandyKingdom",
    "Playable": "True",
    "BuyCost": "1500",
    "CameraWinAnim": "Cam_Minotaur_Win",
    "PIPTransformP1": "PIP_PrincessBubblegum_Player",
    "PIPTransformP2": "PIP_PrincessBubblegum_Opp",
    "CardRemoveAnimTime": "15",
    "CardPlayAnimTime": "23",
    "BigCardPlayAnimTime": "36",
    "Age": "!!Leader_PrincessBubblegum_AGE",
    "Height": "!!Leader_PrincessBubblegum_HEIGHT",
    "Weight": "!!Leader_PrincessBubblegum_WEIGHT",
    "Species": "!!Leader_PrincessBubblegum_SPECIES",
    "Quote": "!!Leader_PrincessBubblegum_QUOTE",
    "LeaderVFX": "Leader_Minotaur_VFX",
    "SaleStartDate1": "ALWAYS"
  },
  {
    "ID": "Leader_LabPrincessBubblegum",
    "Name": "!!Leader_LabPrincessBubblegum_NAME",
    "HPMod": "1",
    "LeaderAbility": "LDR_Draw_1",
    "APThreshold": "15",
    "ActionCard1": "Leader_PrincessBubblegum_01",
    "ActionCard2": "Leader_PrincessBubblegum_02",
    "ActionCard3": "Leader_PrincessBubblegum_03",
    "ActionCard4": "Leader_PrincessBubblegum_04",
    "ActionCard5": "Leader_PrincessBubblegum_05",
    "Prefab": "LabPrincessBubblegum",
    "VO": "PrincessBubblegum",
    "UseChair": "True",
    "ChairOffsetX": "0",
    "ChairOffsetY": "-1.5",
    "CharacterOffsetX": "0",
    "CharacterOffsetY": "3",
    "HeightAdjust": "10",
    "ThoughtBubbleHeightAdjust": "0",
    "QuestPortraitTexture": "PBG_Battle_Image",
    "PortraitTexture": "Portrait_LabPrincessGumball_Hero",
    "VSScreenBackground": "Backdrop_CandyKingdom",
    "SkinOf": "Leader_PrincessBubblegum",
    "BuyableSkin": "True",
    "SkinBuyCost": "1000",
    "CameraWinAnim": "Cam_Minotaur_Win",
    "PIPTransformP1": "PIP_PrincessBubblegum_Player",
    "PIPTransformP2": "PIP_PrincessBubblegum_Opp",
    "CardRemoveAnimTime": "15",
    "CardPlayAnimTime": "23",
    "BigCardPlayAnimTime": "36",
    "Age": "!!Leader_LabPrincessBubblegum_AGE",
    "Height": "!!Leader_LabPrincessBubblegum_HEIGHT",
    "Weight": "!!Leader_LabPrincessBubblegum_WEIGHT",
    "Species": "!!Leader_LabPrincessBubblegum_SPECIES",
    "Quote": "!!Leader_LabPrincessBubblegum_QUOTE",
    "LeaderVFX": "Leader_Minotaur_VFX",
    "SaleStartDate1": "ALWAYS"
  },
  {
    "ID": "Leader_PrincessBubblegumHoliday",
    "Name": "!!Leader_PrincessBubblegumHoliday_NAME",
    "HPMod": "1",
    "LeaderAbility": "LDR_Draw_1",
    "APThreshold": "15",
    "ActionCard1": "Leader_PrincessBubblegum_01",
    "ActionCard2": "Leader_PrincessBubblegum_02",
    "ActionCard3": "Leader_PrincessBubblegum_03",
    "ActionCard4": "Leader_PrincessBubblegum_04",
    "ActionCard5": "Leader_PrincessBubblegum_05",
    "Prefab": "PrincessBubblegum_Sweater",
    "VO": "PrincessBubblegum",
    "UseChair": "True",
    "ChairOffsetX": "0",
    "ChairOffsetY": "-1.5",
    "CharacterOffsetX": "0",
    "CharacterOffsetY": "3",
    "HeightAdjust": "10",
    "ThoughtBubbleHeightAdjust": "0",
    "QuestPortraitTexture": "PBGSweater_Battle_Image",
    "PortraitTexture": "Portrait_SweaterPrincess_Hero",
    "VSScreenBackground": "Backdrop_CandyKingdom",
    "SkinOf": "Leader_PrincessBubblegum",
    "BuyableSkin": "True",
    "SkinBuyCost": "1000",
    "CameraWinAnim": "Cam_Minotaur_Win",
    "PIPTransformP1": "PIP_PrincessBubblegum_Player",
    "PIPTransformP2": "PIP_PrincessBubblegum_Opp",
    "CardRemoveAnimTime": "15",
    "CardPlayAnimTime": "23",
    "BigCardPlayAnimTime": "36",
    "Age": "!!Leader_PrincessBubblegumHoliday_AGE",
    "Height": "!!Leader_PrincessBubblegumHoliday_HEIGHT",
    "Weight": "!!Leader_PrincessBubblegumHoliday_WEIGHT",
    "Species": "!!Leader_PrincessBubblegumHoliday_SPECIES",
    "Quote": "!!Leader_PrincessBubblegumHoliday_QUOTE",
    "LeaderVFX": "Leader_Minotaur_VFX",
    "SaleStartDate1": "ALWAYS"
  },
  {
    "ID": "Leader_PrincessBubblegumZombie",
    "Name": "Zombie Princess Bubblegum",
    "HPMod": "1",
    "LeaderAbility": "LDR_Draw_1",
    "APThreshold": "15",
    "ActionCard1": "Leader_PrincessBubblegum_01",
    "ActionCard2": "Leader_PrincessBubblegum_02",
    "ActionCard3": "Leader_PrincessBubblegum_03",
    "ActionCard4": "Leader_PrincessBubblegum_04",
    "ActionCard5": "Leader_PrincessBubblegum_05",
    "Prefab": "PrincessBubblegum_Zombie",
    "VO": "PrincessBubblegum",
    "UseChair": "True",
    "ChairOffsetX": "0",
    "ChairOffsetY": "-1.5",
    "CharacterOffsetX": "0",
    "CharacterOffsetY": "3",
    "HeightAdjust": "10",
    "ThoughtBubbleHeightAdjust": "0",
    "QuestPortraitTexture": "PBG_Battle_Image_Hal",
    "PortraitTexture": "Portrait_PrincessZombie_Hero",
    "VSScreenBackground": "Backdrop_Cemetery",
    "SkinOf": "Leader_PrincessBubblegum",
    "BuyableSkin": "False",
    "SkinBuyCost": "2000",
    "CameraWinAnim": "Cam_Minotaur_Win",
    "PIPTransformP1": "PIP_PrincessBubblegum_Player",
    "PIPTransformP2": "PIP_PrincessBubblegum_Opp",
    "CardRemoveAnimTime": "15",
    "CardPlayAnimTime": "23",
    "BigCardPlayAnimTime": "36",
    "Age": "!!Leader_PrincessBubblegum_AGE",
    "Height": "!!Leader_PrincessBubblegum_HEIGHT",
    "Weight": "!!Leader_PrincessBubblegum_WEIGHT",
    "Species": "!!Leader_PrincessBubblegum_SPECIES",
    "Quote": "!!Leader_PrincessBubblegum_QUOTE",
    "LeaderVFX": "Leader_Minotaur_VFX",
    "SaleStartDate1": "ALWAYS"
  },
  {
    "ID": "Leader_PrincessBubblegum_GHO",
    "Name": "!!Leader_PrincessBubblegum_GHO_NAME",
    "HPMod": "1",
    "LeaderAbility": "LDR_Draw_1",
    "APThreshold": "15",
    "ActionCard1": "Leader_PrincessBubblegum_01",
    "ActionCard2": "Leader_PrincessBubblegum_02",
    "ActionCard3": "Leader_PrincessBubblegum_03",
    "ActionCard4": "Leader_PrincessBubblegum_04",
    "ActionCard5": "Leader_PrincessBubblegum_05",
    "Prefab": "PrincessBubblegum_Hal",
    "VO": "PrincessBubblegum",
    "UseChair": "True",
    "ChairOffsetX": "0",
    "ChairOffsetY": "-1.5",
    "CharacterOffsetX": "0",
    "CharacterOffsetY": "3",
    "HeightAdjust": "10",
    "ThoughtBubbleHeightAdjust": "0",
    "QuestPortraitTexture": "PBG_Battle_Image_Hal",
    "PortraitTexture": "Portrait_Princess_Hero_Hal",
    "VSScreenBackground": "Backdrop_Cemetery",
    "SkinOf": "Leader_PrincessBubblegum",
    "BuyableSkin": "False",
    "SkinBuyCost": "2000",
    "CameraWinAnim": "Cam_Minotaur_Win",
    "PIPTransformP1": "PIP_PrincessBubblegum_Player",
    "PIPTransformP2": "PIP_PrincessBubblegum_Opp",
    "CardRemoveAnimTime": "15",
    "CardPlayAnimTime": "23",
    "BigCardPlayAnimTime": "36",
    "Age": "!!Leader_PrincessBubblegum_GHO_AGE",
    "Height": "!!Leader_PrincessBubblegum_GHO_HEIGHT",
    "Weight": "!!Leader_PrincessBubblegum_GHO_WEIGHT",
    "Species": "!!Leader_PrincessBubblegum_GHO_SPECIES",
    "Quote": "!!Leader_PrincessBubblegum_GHO_QUOTE",
    "LeaderVFX": "Leader_Minotaur_VFX",
    "SaleStartDate1": "ALWAYS"
  },
  {
    "ID": "Leader_GrandPrixe",
    "Name": "!!Leader_GrandPrixe_NAME",
    "HPMod": "1",
    "LeaderAbility": "LDR_Draw_1",
    "APThreshold": "15",
    "ActionCard1": "Leader_GrandPrixe_01",
    "ActionCard2": "Leader_GrandPrixe_02",
    "ActionCard3": "Leader_GrandPrixe_03",
    "ActionCard4": "Leader_GrandPrixe_04",
    "ActionCard5": "Leader_GrandPrixe_05",
    "Prefab": "GrandPrixe",
    "VO": "GrandPrixe",
    "UseChair": "False",
    "ChairOffsetX": "10",
    "ChairOffsetY": "0",
    "CharacterOffsetX": "0",
    "CharacterOffsetY": "3",
    "HeightAdjust": "20",
    "ThoughtBubbleHeightAdjust": "0",
    "QuestPortraitTexture": "GrandPrix_Battle_Image",
    "PortraitTexture": "Portrait_MagicMan_Hero",
    "VSScreenBackground": "Backdrop_OilRig",
    "Playable": "True",
    "BuyCost": "2500",
    "CameraWinAnim": "Cam_Wizard_Win",
    "PIPTransformP1": "PIP_GrandPrixe_Player",
    "PIPTransformP2": "PIP_GrandPrixe_Opp",
    "CardRemoveAnimTime": "15",
    "CardPlayAnimTime": "23",
    "BigCardPlayAnimTime": "36",
    "Age": "!!Leader_GrandPrixe_AGE",
    "Height": "!!Leader_GrandPrixe_HEIGHT",
    "Weight": "!!Leader_GrandPrixe_WEIGHT",
    "Species": "!!Leader_GrandPrixe_SPECIES",
    "Quote": "!!Leader_GrandPrixe_QUOTE",
    "LeaderVFX": "Leader_Wizard_VFX",
    "SaleStartDate1": "ALWAYS"
  },
  {
    "ID": "Leader_YoungGrandPrixe",
    "Name": "!!Leader_YoungGrandPrixe_NAME",
    "HPMod": "1",
    "LeaderAbility": "LDR_Draw_1",
    "APThreshold": "15",
    "ActionCard1": "Leader_GrandPrixe_01",
    "ActionCard2": "Leader_GrandPrixe_02",
    "ActionCard3": "Leader_GrandPrixe_03",
    "ActionCard4": "Leader_GrandPrixe_04",
    "ActionCard5": "Leader_GrandPrixe_05",
    "Prefab": "YoungGrandPrixe",
    "VO": "GrandPrixe",
    "UseChair": "False",
    "ChairOffsetX": "10",
    "ChairOffsetY": "0",
    "CharacterOffsetX": "0",
    "CharacterOffsetY": "3",
    "HeightAdjust": "20",
    "ThoughtBubbleHeightAdjust": "0",
    "QuestPortraitTexture": "GrandPrix_Battle_Image",
    "PortraitTexture": "Portrait_YoungGrandPrixe_Hero",
    "VSScreenBackground": "Backdrop_OilRig",
    "SkinOf": "Leader_GrandPrixe",
    "BuyableSkin": "True",
    "SkinBuyCost": "1000",
    "CameraWinAnim": "Cam_Wizard_Win",
    "PIPTransformP1": "PIP_GrandPrixe_Player",
    "PIPTransformP2": "PIP_GrandPrixe_Opp",
    "CardRemoveAnimTime": "15",
    "CardPlayAnimTime": "23",
    "BigCardPlayAnimTime": "36",
    "Age": "!!Leader_YoungGrandPrixe_AGE",
    "Height": "!!Leader_YoungGrandPrixe_HEIGHT",
    "Weight": "!!Leader_YoungGrandPrixe_WEIGHT",
    "Species": "!!Leader_YoungGrandPrixe_SPECIES",
    "Quote": "!!Leader_YoungGrandPrixe_QUOTE",
    "LeaderVFX": "Leader_Wizard_VFX",
    "SaleStartDate1": "ALWAYS"
  },
  {
    "ID": "Leader_GrandPrixe_GHO",
    "Name": "!!Leader_GrandPrixe_GHO_NAME",
    "HPMod": "1",
    "LeaderAbility": "LDR_Draw_1",
    "APThreshold": "15",
    "ActionCard1": "Leader_GrandPrixe_01",
    "ActionCard2": "Leader_GrandPrixe_02",
    "ActionCard3": "Leader_GrandPrixe_03",
    "ActionCard4": "Leader_GrandPrixe_04",
    "ActionCard5": "Leader_GrandPrixe_05",
    "Prefab": "GrandPrixe_Hal",
    "VO": "GrandPrixe",
    "UseChair": "False",
    "ChairOffsetX": "10",
    "ChairOffsetY": "0",
    "CharacterOffsetX": "0",
    "CharacterOffsetY": "3",
    "HeightAdjust": "20",
    "ThoughtBubbleHeightAdjust": "0",
    "QuestPortraitTexture": "GrandPrix_Battle_Image_Hal",
    "PortraitTexture": "Portrait_MagicMan_Hero_Hal",
    "VSScreenBackground": "Backdrop_Cemetery",
    "SkinOf": "Leader_GrandPrixe",
    "BuyableSkin": "False",
    "SkinBuyCost": "2000",
    "CameraWinAnim": "Cam_Wizard_Win",
    "PIPTransformP1": "PIP_GrandPrixe_Player",
    "PIPTransformP2": "PIP_GrandPrixe_Opp",
    "CardRemoveAnimTime": "15",
    "CardPlayAnimTime": "23",
    "BigCardPlayAnimTime": "36",
    "Age": "!!Leader_GrandPrixe_GHO_AGE",
    "Height": "!!Leader_GrandPrixe_GHO_HEIGHT",
    "Weight": "!!Leader_GrandPrixe_GHO_WEIGHT",
    "Species": "!!Leader_GrandPrixe_GHO_SPECIES",
    "Quote": "!!Leader_GrandPrixe_GHO_QUOTE",
    "LeaderVFX": "Leader_Wizard_VFX",
    "SaleStartDate1": "ALWAYS"
  },
  {
    "ID": "Leader_BMO",
    "Name": "!!Leader_BMO_NAME",
    "HPMod": "1",
    "LeaderAbility": "LDR_Draw_1",
    "APThreshold": "15",
    "ActionCard1": "Leader_BMO_01",
    "ActionCard2": "Leader_BMO_02",
    "ActionCard3": "Leader_BMO_03",
    "ActionCard4": "Leader_BMO_04",
    "ActionCard5": "Leader_BMO_05",
    "Prefab": "BMO",
    "VO": "BMO",
    "UseChair": "True",
    "ChairOffsetX": "0",
    "ChairOffsetY": "3",
    "CharacterOffsetX": "0",
    "CharacterOffsetY": "3",
    "HeightAdjust": "-7",
    "ThoughtBubbleHeightAdjust": "-110",
    "QuestPortraitTexture": "BMO_Battle_Image",
    "PortraitTexture": "Portrait_Beemo_Hero",
    "VSScreenBackground": "Backdrop_TreehouseInside",
    "Playable": "True",
    "BuyCost": "3600",
    "CameraWinAnim": "Cam_Thief_Win",
    "PIPTransformP1": "PIP_BMO_Player",
    "PIPTransformP2": "PIP_BMO_Opp",
    "CardRemoveAnimTime": "15",
    "CardPlayAnimTime": "23",
    "BigCardPlayAnimTime": "36",
    "Age": "!!Leader_BMO_AGE",
    "Height": "!!Leader_BMO_HEIGHT",
    "Weight": "!!Leader_BMO_WEIGHT",
    "Species": "!!Leader_BMO_SPECIES",
    "Quote": "!!Leader_BMO_QUOTE",
    "LeaderVFX": "Leader_Thief_VFX",
    "SaleStartDate1": "ALWAYS"
  },
  {
    "ID": "Leader_BMO_Beta",
    "Name": "BETA-BMO",
    "HPMod": "1",
    "LeaderAbility": "LDR_Draw_1",
    "APThreshold": "15",
    "ActionCard1": "Leader_BMO_01",
    "ActionCard2": "Leader_BMO_02",
    "ActionCard3": "Leader_BMO_03",
    "ActionCard4": "Leader_BMO_04",
    "ActionCard5": "Leader_BMO_05",
    "Prefab": "BMO_Beta",
    "VO": "BMO",
    "UseChair": "True",
    "ChairOffsetX": "0",
    "ChairOffsetY": "3",
    "CharacterOffsetX": "0",
    "CharacterOffsetY": "3",
    "HeightAdjust": "-7",
    "ThoughtBubbleHeightAdjust": "-110",
    "QuestPortraitTexture": "BMO_Battle_Image",
    "PortraitTexture": "Portrait_Beemo_Beta_Hero",
    "VSScreenBackground": "Backdrop_TreehouseInside",
    "SkinOf": "Leader_BMO",
    "BuyableSkin": "True",
    "SkinBuyCost": "1000",
    "CameraWinAnim": "Cam_Thief_Win",
    "PIPTransformP1": "PIP_BMO_Player",
    "PIPTransformP2": "PIP_BMO_Opp",
    "CardRemoveAnimTime": "15",
    "CardPlayAnimTime": "23",
    "BigCardPlayAnimTime": "36",
    "Age": "!!Leader_BMO_AGE",
    "Height": "!!Leader_BMO_HEIGHT",
    "Weight": "!!Leader_BMO_WEIGHT",
    "Species": "!!Leader_BMO_SPECIES",
    "Quote": "!!Leader_BMO_QUOTE",
    "LeaderVFX": "Leader_Thief_VFX",
    "SaleStartDate1": "ALWAYS"
  },
  {
    "ID": "Leader_BMO_Holiday",
    "Name": "!!Leader_BMO_Holiday_NAME",
    "HPMod": "1",
    "LeaderAbility": "LDR_Draw_1",
    "APThreshold": "15",
    "ActionCard1": "Leader_BMO_Holiday_01",
    "ActionCard2": "Leader_BMO_Holiday_02",
    "ActionCard3": "Leader_BMO_Holiday_03",
    "ActionCard4": "Leader_BMO_Holiday_04",
    "ActionCard5": "Leader_BMO_Holiday_05",
    "Prefab": "BMO_Sweater",
    "VO": "BMO",
    "UseChair": "True",
    "ChairOffsetX": "0",
    "ChairOffsetY": "3",
    "CharacterOffsetX": "0",
    "CharacterOffsetY": "3",
    "HeightAdjust": "-7",
    "ThoughtBubbleHeightAdjust": "-110",
    "QuestPortraitTexture": "BMOSweater_Battle_Image",
    "PortraitTexture": "Portrait_SweaterBMO_Hero",
    "VSScreenBackground": "Backdrop_TreehouseInside",
    "SkinOf": "Leader_BMO",
    "BuyCost": "1000",
    "BuyableSkin": "True",
    "SkinBuyCost": "1000",
    "CameraWinAnim": "Cam_Thief_Win",
    "PIPTransformP1": "PIP_BMO_Player",
    "PIPTransformP2": "PIP_BMO_Opp",
    "CardRemoveAnimTime": "15",
    "CardPlayAnimTime": "23",
    "BigCardPlayAnimTime": "36",
    "Age": "!!Leader_BMO_Holiday_AGE",
    "Height": "!!Leader_BMO_Holiday_HEIGHT",
    "Weight": "!!Leader_BMO_Holiday_WEIGHT",
    "Species": "!!Leader_BMO_Holiday_SPECIES",
    "Quote": "!!Leader_BMO_Holiday_QUOTE",
    "LeaderVFX": "Leader_Thief_VFX",
    "SaleStartDate1": "ALWAYS"
  },
  {
    "ID": "Leader_BMO_GHO",
    "Name": "!!Leader_BMO_GHO_NAME",
    "HPMod": "1",
    "LeaderAbility": "LDR_Draw_1",
    "APThreshold": "15",
    "ActionCard1": "Leader_BMO_GHO_01",
    "ActionCard2": "Leader_BMO_GHO_02",
    "ActionCard3": "Leader_BMO_GHO_03",
    "ActionCard4": "Leader_BMO_GHO_04",
    "ActionCard5": "Leader_BMO_GHO_05",
    "Prefab": "BMO_Hal",
    "VO": "BMO",
    "UseChair": "True",
    "ChairOffsetX": "0",
    "ChairOffsetY": "3",
    "CharacterOffsetX": "0",
    "CharacterOffsetY": "3",
    "HeightAdjust": "-7",
    "ThoughtBubbleHeightAdjust": "-110",
    "QuestPortraitTexture": "BMO_Battle_Image_Hal",
    "PortraitTexture": "Portrait_Beemo_Hero_Hal",
    "VSScreenBackground": "Backdrop_Cemetery",
    "SkinOf": "Leader_BMO",
    "BuyableSkin": "False",
    "SkinBuyCost": "2000",
    "CameraWinAnim": "Cam_Thief_Win",
    "PIPTransformP1": "PIP_BMO_Player",
    "PIPTransformP2": "PIP_BMO_Opp",
    "CardRemoveAnimTime": "15",
    "CardPlayAnimTime": "23",
    "BigCardPlayAnimTime": "36",
    "Age": "!!Leader_BMO_GHO_AGE",
    "Height": "!!Leader_BMO_GHO_HEIGHT",
    "Weight": "!!Leader_BMO_GHO_WEIGHT",
    "Species": "!!Leader_BMO_GHO_SPECIES",
    "Quote": "!!Leader_BMO_GHO_QUOTE",
    "LeaderVFX": "Leader_Thief_VFX",
    "SaleStartDate1": "ALWAYS"
  },
  {
    "ID": "Leader_EarlOfLemongrab",
    "Name": "!!Leader_EarlOfLemongrab_NAME",
    "HPMod": "1",
    "LeaderAbility": "LDR_Draw_1",
    "APThreshold": "15",
    "ActionCard1": "Leader_EarlOfLemongrab_01",
    "ActionCard2": "Leader_EarlOfLemongrab_02",
    "ActionCard3": "Leader_EarlOfLemongrab_03",
    "ActionCard4": "Leader_EarlOfLemongrab_04",
    "ActionCard5": "Leader_EarlOfLemongrab_05",
    "Prefab": "EarlOfLemongrab",
    "VO": "Lemongrab",
    "UseChair": "True",
    "ChairOffsetX": "0",
    "ChairOffsetY": "3",
    "CharacterOffsetX": "0",
    "CharacterOffsetY": "3",
    "HeightAdjust": "2",
    "ThoughtBubbleHeightAdjust": "-90",
    "QuestPortraitTexture": "Lemongrab_Battle_Image",
    "PortraitTexture": "Portrait_Earl_Hero",
    "VSScreenBackground": "Backdrop_Cemetery",
    "Playable": "True",
    "BuyCost": "3900",
    "CameraWinAnim": "Cam_Medusa_Win",
    "PIPTransformP1": "PIP_BMO_Player",
    "PIPTransformP2": "PIP_BMO_Opp",
    "CardRemoveAnimTime": "15",
    "CardPlayAnimTime": "23",
    "BigCardPlayAnimTime": "36",
    "Age": "!!Leader_EarlOfLemongrab_AGE",
    "Height": "!!Leader_EarlOfLemongrab_HEIGHT",
    "Weight": "!!Leader_EarlOfLemongrab_WEIGHT",
    "Species": "!!Leader_EarlOfLemongrab_SPECIES",
    "Quote": "!!Leader_EarlOfLemongrab_QUOTE",
    "LeaderVFX": "Leader_Thief_VFX",
    "SaleStartDate1": "ALWAYS"
  },
  {
    "ID": "Leader_EarlOfLemongrab2",
    "Name": "!!Leader_EarlOfLemongrab_NAME",
    "HPMod": "1",
    "LeaderAbility": "LDR_Draw_1",
    "APThreshold": "15",
    "ActionCard1": "Leader_EarlOfLemongrab_01",
    "ActionCard2": "Leader_EarlOfLemongrab_02",
    "ActionCard3": "Leader_EarlOfLemongrab_03",
    "ActionCard4": "Leader_EarlOfLemongrab_04",
    "ActionCard5": "Leader_EarlOfLemongrab_05",
    "Prefab": "EarlOfLemongrab2",
    "VO": "Lemongrab",
    "UseChair": "True",
    "ChairOffsetX": "0",
    "ChairOffsetY": "3",
    "CharacterOffsetX": "0",
    "CharacterOffsetY": "3",
    "HeightAdjust": "2",
    "ThoughtBubbleHeightAdjust": "-90",
    "QuestPortraitTexture": "Lemongrab_Battle_Image",
    "PortraitTexture": "Portrait_Earl2_Hero",
    "VSScreenBackground": "Backdrop_Cemetery",
    "SkinOf": "Leader_EarlOfLemongrab",
    "BuyableSkin": "True",
    "SkinBuyCost": "2000",
    "CameraWinAnim": "Cam_Medusa_Win",
    "PIPTransformP1": "PIP_BMO_Player",
    "PIPTransformP2": "PIP_BMO_Opp",
    "CardRemoveAnimTime": "15",
    "CardPlayAnimTime": "23",
    "BigCardPlayAnimTime": "36",
    "Age": "!!Leader_EarlOfLemongrab_AGE",
    "Height": "!!Leader_EarlOfLemongrab_HEIGHT",
    "Weight": "!!Leader_EarlOfLemongrab_WEIGHT",
    "Species": "!!Leader_EarlOfLemongrab_SPECIES",
    "Quote": "!!Leader_EarlOfLemongrab_QUOTE",
    "LeaderVFX": "Leader_Thief_VFX",
    "SaleStartDate1": "ALWAYS"
  },
  {
    "ID": "Leader_EarlOfLemongrab_GHO",
    "Name": "Ghost Earl Of Lemongrab",
    "HPMod": "1",
    "LeaderAbility": "LDR_Draw_1",
    "APThreshold": "15",
    "ActionCard1": "Leader_EarlOfLemongrab_01",
    "ActionCard2": "Leader_EarlOfLemongrab_02",
    "ActionCard3": "Leader_EarlOfLemongrab_03",
    "ActionCard4": "Leader_EarlOfLemongrab_04",
    "ActionCard5": "Leader_EarlOfLemongrab_05",
    "Prefab": "EarlOfLemongrab_Hal",
    "VO": "Lemongrab",
    "UseChair": "True",
    "ChairOffsetX": "0",
    "ChairOffsetY": "3",
    "CharacterOffsetX": "0",
    "CharacterOffsetY": "3",
    "HeightAdjust": "2",
    "ThoughtBubbleHeightAdjust": "-90",
    "QuestPortraitTexture": "Lemongrab_Battle_Image",
    "PortraitTexture": "Portrait_Earl_Hero_Hal",
    "VSScreenBackground": "Backdrop_Cemetery",
    "SkinOf": "Leader_EarlOfLemongrab",
    "BuyableSkin": "False",
    "SkinBuyCost": "2000",
    "CameraWinAnim": "Cam_Medusa_Win",
    "PIPTransformP1": "PIP_BMO_Player",
    "PIPTransformP2": "PIP_BMO_Opp",
    "CardRemoveAnimTime": "15",
    "CardPlayAnimTime": "23",
    "BigCardPlayAnimTime": "36",
    "Age": "!!Leader_EarlOfLemongrab_AGE",
    "Height": "!!Leader_EarlOfLemongrab_HEIGHT",
    "Weight": "!!Leader_EarlOfLemongrab_WEIGHT",
    "Species": "!!Leader_EarlOfLemongrab_SPECIES",
    "Quote": "!!Leader_EarlOfLemongrab_QUOTE",
    "LeaderVFX": "Leader_Thief_VFX",
    "SaleStartDate1": "ALWAYS"
  },
  {
    "ID": "Leader_PeppermintButler",
    "Name": "!!Leader_PeppermintButler_NAME",
    "HPMod": "1",
    "LeaderAbility": "LDR_Draw_1",
    "APThreshold": "15",
    "ActionCard1": "Leader_PeppermintButler_01",
    "ActionCard2": "Leader_PeppermintButler_02",
    "ActionCard3": "Leader_PeppermintButler_03",
    "ActionCard4": "Leader_PeppermintButler_04",
    "ActionCard5": "Leader_PeppermintButler_05",
    "Prefab": "PeppermintButler",
    "VO": "PeppermintButler",
    "UseChair": "True",
    "ChairOffsetX": "0",
    "ChairOffsetY": "-2",
    "CharacterOffsetX": "0",
    "CharacterOffsetY": "3",
    "HeightAdjust": "-7",
    "ThoughtBubbleHeightAdjust": "-110",
    "QuestPortraitTexture": "PeppermintButler_Battle_Image",
    "PortraitTexture": "Portrait_peppermint_Hero",
    "VSScreenBackground": "Backdrop_Dungeon",
    "Playable": "True",
    "BuyCost": "4100",
    "CameraWinAnim": "Cam_Thief_Win",
    "PIPTransformP1": "PIP_Finn_Player",
    "PIPTransformP2": "PIP_Finn_Opp",
    "CardRemoveAnimTime": "15",
    "CardPlayAnimTime": "23",
    "BigCardPlayAnimTime": "36",
    "Age": "300+",
    "Height": "15 candy apples tall",
    "Weight": "27 Units",
    "Species": "Candy Person",
    "Quote": "You dare underestimate Dark Magic?",
    "LeaderVFX": "Leader_Thief_VFX",
    "SaleStartDate1": "ALWAYS"
  },
  {
    "ID": "PeppermintButler_WizardCity",
    "Name": "Peppermint Butler",
    "HPMod": "1",
    "LeaderAbility": "LDR_Draw_1",
    "APThreshold": "15",
    "ActionCard1": "Leader_PeppermintButler_01",
    "ActionCard2": "Leader_PeppermintButler_02",
    "ActionCard3": "Leader_PeppermintButler_03",
    "ActionCard4": "Leader_PeppermintButler_04",
    "ActionCard5": "Leader_PeppermintButler_05",
    "Prefab": "PeppermintButler_WizardCity",
    "VO": "PeppermintButler",
    "UseChair": "True",
    "ChairOffsetX": "0",
    "ChairOffsetY": "-2",
    "CharacterOffsetX": "0",
    "CharacterOffsetY": "3",
    "HeightAdjust": "-7",
    "ThoughtBubbleHeightAdjust": "-110",
    "QuestPortraitTexture": "PeppermintButler_Battle_Image",
    "PortraitTexture": "Portrait_PeppermintWizardCity_Hero",
    "VSScreenBackground": "Backdrop_Dungeon",
    "SkinOf": "Leader_PeppermintButler",
    "BuyableSkin": "True",
    "SkinBuyCost": "2000",
    "CameraWinAnim": "Cam_Thief_Win",
    "PIPTransformP1": "PIP_Finn_Player",
    "PIPTransformP2": "PIP_Finn_Opp",
    "CardRemoveAnimTime": "15",
    "CardPlayAnimTime": "23",
    "BigCardPlayAnimTime": "36",
    "Age": "300+",
    "Height": "10 candy apples tall",
    "Weight": "20 Units",
    "Species": "Candy Person",
    "Quote": "To become powerful, I Have to cast the most powerful spell!",
    "LeaderVFX": "Leader_Thief_VFX",
    "SaleStartDate1": "ALWAYS"
  },
  {
    "ID": "Leader_PeppermintButler_GHO",
    "Name": "Ghost Peppermint Butler",
    "HPMod": "1",
    "LeaderAbility": "LDR_Draw_1",
    "APThreshold": "15",
    "ActionCard1": "Leader_PeppermintButler_01",
    "ActionCard2": "Leader_PeppermintButler_02",
    "ActionCard3": "Leader_PeppermintButler_03",
    "ActionCard4": "Leader_PeppermintButler_04",
    "ActionCard5": "Leader_PeppermintButler_05",
    "ActionCard6": "Leader_Banana_01",
    "Prefab": "PeppermintButler_Hal",
    "VO": "PeppermintButler",
    "UseChair": "True",
    "ChairOffsetX": "0",
    "ChairOffsetY": "-1.5",
    "CharacterOffsetX": "0",
    "CharacterOffsetY": "3",
    "HeightAdjust": "10",
    "ThoughtBubbleHeightAdjust": "0",
    "QuestPortraitTexture": "PeppermintButler_Battle_Image",
    "PortraitTexture": "Portrait_Peppermint_Hal_Hero",
    "VSScreenBackground": "Backdrop_Cemetery",
    "SkinOf": "Leader_PeppermintButler",
    "BuyableSkin": "False",
    "SkinBuyCost": "2000",
    "CameraWinAnim": "Cam_Thief_Win",
    "PIPTransformP1": "PIP_Finn_Player",
    "PIPTransformP2": "PIP_Finn_Opp",
    "CardRemoveAnimTime": "15",
    "CardPlayAnimTime": "23",
    "BigCardPlayAnimTime": "36",
    "Age": "300+",
    "Height": "15 candy apples tall",
    "Weight": "27 Units",
    "Species": "Candy Person",
    "Quote": "!!Leader_PeppermintButler_QUOTE",
    "LeaderVFX": "Leader_Thief_VFX",
    "SaleStartDate1": "ALWAYS"
  },
  {
    "ID": "Leader_LadyRainicorn",
    "Name": "Lady Rainicorn",
    "HPMod": "1",
    "LeaderAbility": "LDR_Draw_1",
    "APThreshold": "15",
    "ActionCard1": "Leader_LadyCorn_01",
    "ActionCard2": "Leader_LadyCorn_02",
    "ActionCard3": "Leader_LadyCorn_03",
    "ActionCard4": "Leader_LadyCorn_04",
    "ActionCard5": "Leader_LadyCorn_05",
    "Prefab": "LadyRainicorn",
    "VO": "LadyCorn",
    "UseChair": "True",
    "ChairOffsetX": "0",
    "ChairOffsetY": "-2",
    "CharacterOffsetX": "0",
    "CharacterOffsetY": "3",
    "HeightAdjust": "-7",
    "ThoughtBubbleHeightAdjust": "-110",
    "QuestPortraitTexture": "LadyCorn_Battle_Image",
    "PortraitTexture": "Portrait_LadyRainicorn_Hero",
    "VSScreenBackground": "Backdrop_Forest",
    "Playable": "True",
    "BuyCost": "3100",
    "CameraWinAnim": "Cam_Wizard_Win",
    "PIPTransformP1": "PIP_GrandPrixe_Player",
    "PIPTransformP2": "PIP_GrandPrixe_Opp",
    "CardRemoveAnimTime": "15",
    "CardPlayAnimTime": "23",
    "BigCardPlayAnimTime": "36",
    "Age": "30",
    "Height": "Pretty long",
    "Weight": "Unknown",
    "Species": "Rainicorn",
    "Quote": "Jake taught me this one… I'm pretty good at it!",
    "LeaderVFX": "Leader_Wizard_VFX",
    "SaleStartDate1": "ALWAYS"
  },
  {
    "ID": "Leader_Hunson",
    "Name": "Hunson Abadeer",
    "HPMod": "1",
    "LeaderAbility": "LDR_Draw_1",
    "APThreshold": "15",
    "ActionCard1": "Leader_Hunson_01",
    "ActionCard2": "Leader_Hunson_02",
    "ActionCard3": "Leader_Hunson_03",
    "ActionCard4": "Leader_Hunson_04",
    "ActionCard5": "Leader_Hunson_05",
    "Prefab": "HunsonAbadeer",
    "VO": "HunsonAbadeer",
    "UseChair": "True",
    "ChairOffsetX": "0",
    "ChairOffsetY": "-1.5",
    "CharacterOffsetX": "0",
    "CharacterOffsetY": "3",
    "HeightAdjust": "0",
    "ThoughtBubbleHeightAdjust": "0",
    "QuestPortraitTexture": "Hunson_Battle_Image",
    "PortraitTexture": "Portrait_Hunson_Hero",
    "VSScreenBackground": "Backdrop_Marcelines",
    "Playable": "True",
    "BuyCost": "3700",
    "CameraWinAnim": "Cam_Dwarf_Win",
    "PIPTransformP1": "PIP_Marceline_Player",
    "PIPTransformP2": "PIP_Marceline_Opp",
    "CardRemoveAnimTime": "15",
    "CardPlayAnimTime": "23",
    "BigCardPlayAnimTime": "36",
    "Age": "Older Than Time itself",
    "Height": "Heavily Depends",
    "Weight": "Unknown",
    "Species": "Demon",
    "Quote": "Ah, Card Wars... a game so pretty",
    "LeaderVFX": "Leader_Dwarf_VFX",
    "SaleStartDate1": "ALWAYS"
  },
  {
    "ID": "Leader_BananaGuard",
    "Name": "Banana Guard",
    "HPMod": "1",
    "LeaderAbility": "LDR_Draw_1",
    "APThreshold": "15",
    "ActionCard1": "Leader_Banana_01",
    "ActionCard2": "Leader_Banana_02",
    "ActionCard3": "Leader_Banana_03",
    "ActionCard4": "Leader_Banana_04",
    "ActionCard5": "Leader_Banana_05",
    "Prefab": "BananaGuard",
    "VO": "BananaGuard",
    "UseChair": "True",
    "ChairOffsetX": "0",
    "ChairOffsetY": "-1.5",
    "CharacterOffsetX": "0",
    "CharacterOffsetY": "3",
    "HeightAdjust": "0",
    "ThoughtBubbleHeightAdjust": "0",
    "QuestPortraitTexture": "Banana_Battle_Image",
    "PortraitTexture": "Portrait_BananaGuard_Hero",
    "VSScreenBackground": "Backdrop_CandyKingdom",
    "Playable": "True",
    "BuyCost": "3400",
    "CameraWinAnim": "Cam_Wizard_Win",
    "PIPTransformP1": "PIP_GrandPrixe_Player",
    "PIPTransformP2": "PIP_GrandPrixe_Opp",
    "CardRemoveAnimTime": "15",
    "CardPlayAnimTime": "23",
    "BigCardPlayAnimTime": "36",
    "Age": "Adult",
    "Height": "Tall",
    "Weight": "31 Units",
    "Species": "Banana",
    "Quote": "Banana Guards never retreat... unless they get confused. Which I am... right now.",
    "LeaderVFX": "Leader_Wizard_VFX",
    "SaleStartDate1": "ALWAYS"
  },
  {
    "ID": "Leader_BananaGuard_GHO",
    "Name": "Ghost Banana Guard",
    "HPMod": "1",
    "LeaderAbility": "LDR_Draw_1",
    "APThreshold": "15",
    "ActionCard1": "Leader_Banana_01",
    "ActionCard2": "Leader_Banana_02",
    "ActionCard3": "Leader_Banana_03",
    "ActionCard4": "Leader_Banana_04",
    "ActionCard5": "Leader_Banana_05",
    "Prefab": "BananaGuard_Hal",
    "VO": "BananaGuard",
    "UseChair": "True",
    "ChairOffsetX": "0",
    "ChairOffsetY": "-1.5",
    "CharacterOffsetX": "0",
    "CharacterOffsetY": "3",
    "HeightAdjust": "0",
    "ThoughtBubbleHeightAdjust": "0",
    "QuestPortraitTexture": "Banana_Battle_Image",
    "PortraitTexture": "Portrait_BananaGuard_Hero_Hal",
    "VSScreenBackground": "Backdrop_CandyKingdom",
    "SkinOf": "Leader_BananaGuard",
    "BuyableSkin": "False",
    "SkinBuyCost": "2000",
    "CameraWinAnim": "Cam_Wizard_Win",
    "PIPTransformP1": "PIP_GrandPrixe_Player",
    "PIPTransformP2": "PIP_GrandPrixe_Opp",
    "CardRemoveAnimTime": "15",
    "CardPlayAnimTime": "23",
    "BigCardPlayAnimTime": "36",
    "Age": "Adult",
    "Height": "Tall",
    "Weight": "31 Units",
    "Species": "Banana",
    "Quote": "Banana Guards never retreat... unless they get confused. Which I am... right now.",
    "LeaderVFX": "Leader_Wizard_VFX",
    "SaleStartDate1": "ALWAYS"
  },
  {
    "ID": "Leader_BananaGuardZombie",
    "Name": "Zombie Banana Guard",
    "HPMod": "1",
    "LeaderAbility": "LDR_Draw_1",
    "APThreshold": "15",
    "ActionCard1": "Leader_Banana_01",
    "ActionCard2": "Leader_Banana_02",
    "ActionCard3": "Leader_Banana_03",
    "ActionCard4": "Leader_Banana_04",
    "ActionCard5": "Leader_Banana_05",
    "Prefab": "BananaGuard_Zombie",
    "VO": "BananaGuard",
    "UseChair": "True",
    "ChairOffsetX": "0",
    "ChairOffsetY": "-1.5",
    "CharacterOffsetX": "0",
    "CharacterOffsetY": "3",
    "HeightAdjust": "0",
    "ThoughtBubbleHeightAdjust": "0",
    "QuestPortraitTexture": "Banana_Battle_Image",
    "PortraitTexture": "Portrait_BananaGuardZombie_Hero",
    "VSScreenBackground": "Backdrop_CandyKingdom",
    "SkinOf": "Leader_BananaGuard",
    "BuyableSkin": "False",
    "SkinBuyCost": "2000",
    "CameraWinAnim": "Cam_Wizard_Win",
    "PIPTransformP1": "PIP_GrandPrixe_Player",
    "PIPTransformP2": "PIP_GrandPrixe_Opp",
    "CardRemoveAnimTime": "15",
    "CardPlayAnimTime": "23",
    "BigCardPlayAnimTime": "36",
    "Age": "Adult",
    "Height": "Tall",
    "Weight": "31 Units",
    "Species": "Banana",
    "Quote": "Banana Guards never retreat... unless they get confused. Which I am... right now.",
    "LeaderVFX": "Leader_Wizard_VFX",
    "SaleStartDate1": "ALWAYS"
  },
  {
    "ID": "Leader_MagicMan",
    "Name": "Magic Man",
    "HPMod": "1",
    "LeaderAbility": "LDR_Draw_1",
    "APThreshold": "15",
    "ActionCard1": "Leader_MagicMan_01",
    "ActionCard2": "Leader_MagicMan_02",
    "ActionCard3": "Leader_MagicMan_03",
    "ActionCard4": "Leader_MagicMan_04",
    "ActionCard5": "Leader_MagicMan_05",
    "Prefab": "MagicMan",
    "VO": "MagicMan",
    "UseChair": "True",
    "ChairOffsetX": "0",
    "ChairOffsetY": "-1.5",
    "CharacterOffsetX": "0",
    "CharacterOffsetY": "3",
    "HeightAdjust": "2",
    "ThoughtBubbleHeightAdjust": "-90",
    "QuestPortraitTexture": "Finn_Battle_Image",
    "PortraitTexture": "Portrait_MagicManHuman_Hero",
    "VSScreenBackground": "Backdrop_Forest",
    "Playable": "True",
    "BuyCost": "6500",
    "CameraWinAnim": "Cam_Warrior_Win",
    "PIPTransformP1": "PIP_Finn_Player",
    "PIPTransformP2": "PIP_Finn_Opp",
    "CardRemoveAnimTime": "15",
    "CardPlayAnimTime": "23",
    "BigCardPlayAnimTime": "36",
    "Age": "65",
    "Height": "!!Leader_Finn_HEIGHT",
    "Weight": "!!Leader_Finn_WEIGHT",
    "Species": "Wizard",
    "Quote": "Let's Play",
    "LeaderVFX": "Leader_Warrior_VFX"
  },
  {
    "ID": "Leader_Gunter",
    "Name": "Gunter",
    "HPMod": "1",
    "LeaderAbility": "LDR_Draw_1",
    "APThreshold": "15",
    "ActionCard1": "Leader_Gunter_01",
    "ActionCard2": "Leader_Gunter_02",
    "ActionCard3": "Leader_Gunter_03",
    "ActionCard4": "Leader_Gunter_04",
    "ActionCard5": "Leader_Gunter_05",
    "Prefab": "Gunter",
    "VO": "Gunter",
    "UseChair": "True",
    "ChairOffsetX": "10",
    "ChairOffsetY": "0",
    "CharacterOffsetX": "0",
    "CharacterOffsetY": "3",
    "HeightAdjust": "20",
    "ThoughtBubbleHeightAdjust": "0",
    "QuestPortraitTexture": "Gunter_Battle_Image",
    "PortraitTexture": "Portrait_Gunter_Hero",
    "VSScreenBackground": "Backdrop_IceCave",
    "Playable": "True",
    "BuyCost": "3000",
    "CameraWinAnim": "Cam_Wizard_Win",
    "PIPTransformP1": "PIP_Finn_Player",
    "PIPTransformP2": "PIP_Finn_Opp",
    "CardRemoveAnimTime": "15",
    "CardPlayAnimTime": "23",
    "BigCardPlayAnimTime": "36",
    "Age": "Unknown",
    "Height": "Small",
    "Weight": "Tiny",
    "Species": "Penguin",
    "Quote": "Vaah Vaah Vaaah!",
    "LeaderVFX": "Leader_Wizard_VFX",
    "SaleStartDate1": "ALWAYS"
  },
  {
    "ID": "Leader_Ash",
    "Name": "Ash",
    "HPMod": "1",
    "LeaderAbility": "LDR_Draw_1",
    "APThreshold": "15",
    "ActionCard1": "Leader_Ash_01",
    "ActionCard2": "Leader_Ash_02",
    "ActionCard3": "Leader_Ash_03",
    "ActionCard4": "Leader_Ash_04",
    "ActionCard5": "Leader_Ash_05",
    "Prefab": "Ash",
    "VO": "Ash",
    "UseChair": "True",
    "ChairOffsetX": "0",
    "ChairOffsetY": "-1.5",
    "CharacterOffsetX": "0",
    "CharacterOffsetY": "3",
    "HeightAdjust": "2",
    "ThoughtBubbleHeightAdjust": "-90",
    "QuestPortraitTexture": "Finn_Battle_Image",
    "PortraitTexture": "Portrait_Ash_Hero",
    "VSScreenBackground": "Backdrop_Forest",
    "Playable": "True",
    "BuyCost": "4000",
    "CameraWinAnim": "Cam_Warrior_Win",
    "PIPTransformP1": "PIP_Finn_Player",
    "PIPTransformP2": "PIP_Finn_Opp",
    "CardRemoveAnimTime": "15",
    "CardPlayAnimTime": "23",
    "BigCardPlayAnimTime": "36",
    "Age": "1200+",
    "Height": "!!Leader_Marceline_HEIGHT",
    "Weight": "!!Leader_Marceline_WEIGHT",
    "Species": "Wizard",
    "Quote": "IT'S SHOW TIME!!!",
    "LeaderVFX": "Leader_Warrior_VFX",
    "SaleStartDate1": "ALWAYS"
  },
  {
    "ID": "Leader_CinnamonBun",
    "Name": "Cinnamon Bun",
    "HPMod": "1",
    "LeaderAbility": "LDR_Draw_1",
    "APThreshold": "15",
    "ActionCard1": "Leader_Cinnamon_01",
    "ActionCard2": "Leader_Cinnamon_02",
    "ActionCard3": "Leader_Cinnamon_03",
    "ActionCard4": "Leader_Cinnamon_04",
    "ActionCard5": "Leader_Cinnamon_05",
    "Prefab": "CinnamonBun",
    "VO": "CinnamonBun",
    "UseChair": "True",
    "ChairOffsetX": "0",
    "ChairOffsetY": "-2",
    "CharacterOffsetX": "0",
    "CharacterOffsetY": "3",
    "HeightAdjust": "-7",
    "ThoughtBubbleHeightAdjust": "-110",
    "QuestPortraitTexture": "Bun_Battle_Image",
    "PortraitTexture": "Portrait_CinnamonBun_Hero",
    "VSScreenBackground": "Backdrop_Cemetery",
    "Playable": "True",
    "BuyCost": "3200",
    "CameraWinAnim": "Cam_Thief_Win",
    "PIPTransformP1": "PIP_Finn_Player",
    "PIPTransformP2": "PIP_Finn_Opp",
    "CardRemoveAnimTime": "15",
    "CardPlayAnimTime": "23",
    "BigCardPlayAnimTime": "36",
    "Age": "700+",
    "Height": "41 Cinnamon rolls Tall",
    "Weight": "46 Units",
    "Species": "Candy Person",
    "Quote": "Uh..How do you play this game?",
    "LeaderVFX": "Leader_Thief_VFX",
    "SaleStartDate1": "ALWAYS"
  },
  {
    "ID": "Leader_CinnamonBun_Zombie",
    "Name": "Zombie Cinnamon Bun",
    "HPMod": "1",
    "LeaderAbility": "LDR_Draw_1",
    "APThreshold": "15",
    "ActionCard1": "Leader_Cinnamon_01",
    "ActionCard2": "Leader_Cinnamon_02",
    "ActionCard3": "Leader_Cinnamon_03",
    "ActionCard4": "Leader_Cinnamon_04",
    "ActionCard5": "Leader_Cinnamon_05",
    "Prefab": "CinnamonBun_Zombie",
    "VO": "CinnamonBun",
    "UseChair": "True",
    "ChairOffsetX": "0",
    "ChairOffsetY": "-2",
    "CharacterOffsetX": "0",
    "CharacterOffsetY": "3",
    "HeightAdjust": "-7",
    "ThoughtBubbleHeightAdjust": "-110",
    "QuestPortraitTexture": "Bun_Battle_Image",
    "PortraitTexture": "Portrait_CinnamonBunZombie_Hero",
    "VSScreenBackground": "Backdrop_Cemetery",
    "SkinOf": "Leader_CinnamonBun",
    "BuyableSkin": "False",
    "SkinBuyCost": "2000",
    "CameraWinAnim": "Cam_Thief_Win",
    "PIPTransformP1": "PIP_Finn_Player",
    "PIPTransformP2": "PIP_Finn_Opp",
    "CardRemoveAnimTime": "15",
    "CardPlayAnimTime": "23",
    "BigCardPlayAnimTime": "36",
    "Age": "700+",
    "Height": "41 Cinnamon rolls Tall",
    "Weight": "46 Units",
    "Species": "Candy Person",
    "Quote": "Uh..How do you play this game?",
    "LeaderVFX": "Leader_Thief_VFX",
    "SaleStartDate1": "ALWAYS"
  },
  {
    "ID": "Leader_TreasureCat",
    "Name": "Treasure Cat",
    "HPMod": "1",
    "LeaderAbility": "LDR_Draw_1",
    "APThreshold": "15",
    "ActionCard1": "Leader_Cat_01",
    "ActionCard2": "Leader_Cat_02",
    "ActionCard3": "Leader_Cat_03",
    "ActionCard4": "Leader_Cat_04",
    "ActionCard5": "Leader_Cat_05",
    "Prefab": "TreasureCat",
    "VO": "TreasureCat",
    "UseChair": "True",
    "ChairOffsetX": "0",
    "ChairOffsetY": "-2",
    "CharacterOffsetX": "0",
    "CharacterOffsetY": "3",
    "HeightAdjust": "-7",
    "ThoughtBubbleHeightAdjust": "-110",
    "QuestPortraitTexture": "BMO_Battle_Image",
    "PortraitTexture": "Portrait_TreasureCat_Hero",
    "VSScreenBackground": "Backdrop_Dungeon",
    "BuyCost": "6500",
    "CameraWinAnim": "Cam_Wizard_Win",
    "PIPTransformP1": "PIP_GrandPrixe_Player",
    "PIPTransformP2": "PIP_GrandPrixe_Opp",
    "CardRemoveAnimTime": "15",
    "CardPlayAnimTime": "23",
    "BigCardPlayAnimTime": "36",
    "Age": "45",
    "Height": "Tall",
    "Weight": "Narrow-Chest",
    "Species": "Cat",
    "Quote": "Meow",
    "LeaderVFX": "Leader_Wizard_VFX",
    "SaleStartDate1": "ALWAYS"
  },
  {
    "ID": "Leader_MrCupcake",
    "Name": "Mr. Cupcake",
    "HPMod": "1",
    "LeaderAbility": "LDR_Draw_1",
    "APThreshold": "15",
    "ActionCard1": "Leader_MrMuffin_01",
    "ActionCard2": "Leader_MrMuffin_02",
    "ActionCard3": "Leader_MrMuffin_03",
    "ActionCard4": "Leader_MrMuffin_04",
    "ActionCard5": "Leader_MrMuffin_05",
    "Prefab": "MrCupcake",
    "VO": "GrandPrixe",
    "UseChair": "False",
    "ChairOffsetX": "10",
    "ChairOffsetY": "0",
    "CharacterOffsetX": "0",
    "CharacterOffsetY": "3",
    "HeightAdjust": "20",
    "ThoughtBubbleHeightAdjust": "0",
    "QuestPortraitTexture": "GrandPrix_Battle_Image",
    "PortraitTexture": "Portrait_MrCupcake_Hero",
    "VSScreenBackground": "Backdrop_CandyKingdom",
    "Playable": "True",
    "BuyCost": "100000",
    "CameraWinAnim": "Cam_Wizard_Win",
    "PIPTransformP1": "PIP_GrandPrixe_Player",
    "PIPTransformP2": "PIP_GrandPrixe_Opp",
    "CardRemoveAnimTime": "15",
    "CardPlayAnimTime": "23",
    "BigCardPlayAnimTime": "36",
    "Age": "53-57",
    "Height": "Cream",
    "Weight": "Cake",
    "Species": "Muffin",
    "Quote": "I'M STRONG",
    "LeaderVFX": "Leader_Wizard_VFX"
  },
  {
    "ID": "Leader_Lich",
    "Name": "The Lich",
    "HPMod": "1",
    "LeaderAbility": "LDR_Draw_1",
    "APThreshold": "15",
    "ActionCard1": "Leader_Lich_01",
    "ActionCard2": "Leader_Lich_02",
    "ActionCard3": "Leader_Lich_03",
    "ActionCard4": "Leader_Lich_04",
    "ActionCard5": "Leader_Lich_05",
    "Prefab": "Lich",
    "VO": "GrandPrixe",
    "UseChair": "False",
    "ChairOffsetX": "10",
    "ChairOffsetY": "0",
    "CharacterOffsetX": "0",
    "CharacterOffsetY": "3",
    "HeightAdjust": "20",
    "ThoughtBubbleHeightAdjust": "0",
    "QuestPortraitTexture": "GrandPrix_Battle_Image",
    "PortraitTexture": "Portrait_Lich_Hero",
    "VSScreenBackground": "Backdrop_Cemetery",
    "Playable": "True",
    "BuyCost": "66000",
    "CameraWinAnim": "Cam_Wizard_Win",
    "PIPTransformP1": "PIP_GrandPrixe_Player",
    "PIPTransformP2": "PIP_GrandPrixe_Opp",
    "CardRemoveAnimTime": "15",
    "CardPlayAnimTime": "23",
    "BigCardPlayAnimTime": "36",
    "Age": "Over One Billion Pre Big-Bang",
    "Height": "Skull Man",
    "Weight": "Sorcerer",
    "Species": "Monster",
    "Quote": "GOOD NIGHTMARES",
    "LeaderVFX": "Leader_Wizard_VFX",
    "SaleStartDate1": "ALWAYS"
  },
  {
    "ID": "Leader_Prismo",
    "Name": "Prismo",
    "HPMod": "1",
    "LeaderAbility": "LDR_Draw_1",
    "APThreshold": "15",
    "ActionCard1": "Leader_Prismo_01",
    "ActionCard2": "Leader_Prismo_02",
    "ActionCard3": "Leader_Prismo_03",
    "ActionCard4": "Leader_Prismo_04",
    "ActionCard5": "Leader_Prismo_05",
    "Prefab": "Prismo",
    "VO": "GrandPrixe",
    "UseChair": "False",
    "ChairOffsetX": "10",
    "ChairOffsetY": "0",
    "CharacterOffsetX": "0",
    "CharacterOffsetY": "3",
    "HeightAdjust": "20",
    "ThoughtBubbleHeightAdjust": "0",
    "QuestPortraitTexture": "GrandPrix_Battle_Image",
    "PortraitTexture": "Portrait_Prismo_Hero",
    "VSScreenBackground": "Backdrop_Cemetery",
    "Playable": "True",
    "BuyCost": "66000",
    "CameraWinAnim": "Cam_Warrior_Win",
    "PIPTransformP1": "PIP_Finn_Player",
    "PIPTransformP2": "PIP_Finn_Opp",
    "CardRemoveAnimTime": "15",
    "CardPlayAnimTime": "23",
    "BigCardPlayAnimTime": "36",
    "Age": "Unknown",
    "Height": "Wishmaster",
    "Weight": "Pink Stickman",
    "Species": "Humanoid",
    "Quote": "MY FAVORITE CARD WARS!!!!",
    "LeaderVFX": "Leader_Warrior_VFX",
    "SaleStartDate1": "ALWAYS"
  },
  {
    "ID": "Leader_HuntressWizard",
    "Name": "Huntress Wizard",
    "HPMod": "1",
    "LeaderAbility": "LDR_Draw_1",
    "APThreshold": "15",
    "ActionCard1": "Leader_Huntress_01",
    "ActionCard2": "Leader_Huntress_02",
    "ActionCard3": "Leader_Huntress_03",
    "ActionCard4": "Leader_Huntress_04",
    "ActionCard5": "Leader_Huntress_05",
    "Prefab": "huntresswizard",
    "VO": "Huntress",
    "UseChair": "False",
    "ChairOffsetX": "10",
    "ChairOffsetY": "0",
    "CharacterOffsetX": "0",
    "CharacterOffsetY": "3",
    "HeightAdjust": "20",
    "ThoughtBubbleHeightAdjust": "0",
    "QuestPortraitTexture": "GrandPrix_Battle_Image",
    "PortraitTexture": "Portrait_Huntress_Hero",
    "VSScreenBackground": "Backdrop_Cemetery",
    "Playable": "True",
    "BuyCost": "66000",
    "CameraWinAnim": "Cam_Warrior_Win",
    "PIPTransformP1": "PIP_Finn_Player",
    "PIPTransformP2": "PIP_Finn_Opp",
    "CardRemoveAnimTime": "15",
    "CardPlayAnimTime": "23",
    "BigCardPlayAnimTime": "36",
    "Age": "Unknown",
    "Height": "Huntress",
    "Weight": "Wizard",
    "Species": "Plant Humanoid",
    "Quote": "You are a soft version of me. Weak.",
    "LeaderVFX": "Leader_Warrior_VFX"
  },
  {
    "ID": "Leader_PoweredJk",
    "Name": "Cooler Jake",
    "HPMod": "1",
    "LeaderAbility": "LDR_Draw_1",
    "APThreshold": "15",
    "ActionCard1": "Leader_JakePwr_01",
    "ActionCard2": "Leader_JakePwr_02",
    "ActionCard3": "Leader_JakePwr_03",
    "ActionCard4": "Leader_JakePwr_04",
    "ActionCard5": "Leader_JakePwr_05",
    "Prefab": "PoweredJk",
    "VO": "Jake",
    "UseChair": "False",
    "ChairOffsetX": "0",
    "ChairOffsetY": "-1.5",
    "CharacterOffsetX": "0",
    "CharacterOffsetY": "3",
    "HeightAdjust": "2",
    "ThoughtBubbleHeightAdjust": "-90",
    "QuestPortraitTexture": "Finn_Battle_Image",
    "PortraitTexture": "Portrait_PwrJk_Hero",
    "VSScreenBackground": "Backdrop_Treehouse2",
    "Playable": "True",
    "BuyCost": "24000",
    "CameraWinAnim": "Cam_Warrior_Win",
    "PIPTransformP1": "PIP_Finn_Player",
    "PIPTransformP2": "PIP_Finn_Opp",
    "CardRemoveAnimTime": "15",
    "CardPlayAnimTime": "23",
    "BigCardPlayAnimTime": "36",
    "Age": "!!Leader_JakeKing_AGE",
    "Height": "!!Leader_JakeKing_HEIGHT",
    "Weight": "!!Leader_JakeKing_WEIGHT",
    "Species": "!!Leader_JakeKing_SPECIES",
    "Quote": "!!Leader_JakeKing_QUOTE",
    "LeaderVFX": "Leader_Warrior_VFX",
    "SaleStartDate1": "ALWAYS"
  },
  {
    "ID": "Leader_PoweredFn",
    "Name": "Prime Finn The Human",
    "HPMod": "1",
    "LeaderAbility": "LDR_Draw_1",
    "APThreshold": "15",
    "ActionCard1": "Leader_FinnPwr_01",
    "ActionCard2": "Leader_FinnPwr_02",
    "ActionCard3": "Leader_FinnPwr_03",
    "ActionCard4": "Leader_FinnPwr_04",
    "ActionCard5": "Leader_FinnPwr_05",
    "Prefab": "PrimeFinn",
    "VO": "Finn",
    "UseChair": "True",
    "ChairOffsetX": "0",
    "ChairOffsetY": "-1.5",
    "CharacterOffsetX": "0",
    "CharacterOffsetY": "3",
    "HeightAdjust": "2",
    "ThoughtBubbleHeightAdjust": "-90",
    "QuestPortraitTexture": "Finn_Battle_Image",
    "PortraitTexture": "Portrait_PwrFn_Hero",
    "VSScreenBackground": "Backdrop_Treehouse",
    "Playable": "True",
    "BuyCost": "30000",
    "CameraWinAnim": "Cam_Warrior_Win",
    "PIPTransformP1": "PIP_Finn_Player",
    "PIPTransformP2": "PIP_Finn_Opp",
    "CardRemoveAnimTime": "15",
    "CardPlayAnimTime": "23",
    "BigCardPlayAnimTime": "36",
    "Age": "!!Leader_Finn_AGE",
    "Height": "!!Leader_Finn_HEIGHT",
    "Weight": "!!Leader_Finn_WEIGHT",
    "Species": "!!Leader_Finn_SPECIES",
    "Quote": "!!Leader_Finn_QUOTE",
    "LeaderVFX": "Leader_Warrior_VFX",
    "SaleStartDate1": "ALWAYS"
  },
  {
    "ID": "Leader_IceKing_Pwr",
    "Name": "Powered Ice King",
    "HPMod": "1",
    "LeaderAbility": "LDR_Draw_1",
    "APThreshold": "15",
    "ActionCard1": "Leader_IceKingPwr_01",
    "ActionCard2": "Leader_IceKingPwr_02",
    "ActionCard3": "Leader_IceKingPwr_03",
    "ActionCard4": "Leader_IceKingPwr_04",
    "ActionCard5": "Leader_IceKingPwr_05",
    "Prefab": "IceKing_Pwr",
    "VO": "IceKing",
    "UseChair": "False",
    "ChairOffsetX": "0",
    "ChairOffsetY": "0",
    "CharacterOffsetX": "0",
    "CharacterOffsetY": "3",
    "HeightAdjust": "10",
    "ThoughtBubbleHeightAdjust": "0",
    "QuestPortraitTexture": "IceKing_Battle_Image",
    "PortraitTexture": "Portrait_IceKingPwr_Hero",
    "VSScreenBackground": "Backdrop_IceCave",
    "Playable": "True",
    "BuyCost": "2800",
    "CameraWinAnim": "Cam_Druid_Win",
    "PIPTransformP1": "PIP_IceKing_Player",
    "PIPTransformP2": "PIP_IceKing_Opp",
    "CardRemoveAnimTime": "15",
    "CardPlayAnimTime": "23",
    "BigCardPlayAnimTime": "36",
    "Age": "!!Leader_IceKing_AGE",
    "Height": "!!Leader_IceKing_HEIGHT",
    "Weight": "!!Leader_IceKing_WEIGHT",
    "Species": "!!Leader_IceKing_SPECIES",
    "Quote": "!!Leader_IceKing_QUOTE",
    "LeaderVFX": "Leader_Druid_VFX"
  },
  {
    "ID": "Leader_Marceline_Pwr",
    "Name": "Powered Marceline",
    "HPMod": "1",
    "LeaderAbility": "LDR_Draw_1",
    "APThreshold": "15",
    "ActionCard1": "Leader_MarcelinePwr_01",
    "ActionCard2": "Leader_MarcelinePwr_02",
    "ActionCard3": "Leader_MarcelinePwr_03",
    "ActionCard4": "Leader_MarcelinePwr_04",
    "ActionCard5": "Leader_MarcelinePwr_05",
    "Prefab": "Marceline_Pwr",
    "VO": "Marceline",
    "UseChair": "True",
    "ChairOffsetX": "0",
    "ChairOffsetY": "-1.5",
    "CharacterOffsetX": "0",
    "CharacterOffsetY": "3",
    "HeightAdjust": "0",
    "ThoughtBubbleHeightAdjust": "0",
    "QuestPortraitTexture": "Marceline_Battle_Image",
    "PortraitTexture": "Portrait_MarcelinePwr_Hero",
    "VSScreenBackground": "Backdrop_Marcelines",
    "Playable": "True",
    "BuyCost": "2700",
    "CameraWinAnim": "Cam_Dwarf_Win",
    "PIPTransformP1": "PIP_Marceline_Player",
    "PIPTransformP2": "PIP_Marceline_Opp",
    "CardRemoveAnimTime": "15",
    "CardPlayAnimTime": "23",
    "BigCardPlayAnimTime": "36",
    "Age": "!!Leader_Marceline_AGE",
    "Height": "!!Leader_Marceline_HEIGHT",
    "Weight": "!!Leader_Marceline_WEIGHT",
    "Species": "!!Leader_Marceline_SPECIES",
    "Quote": "!!Leader_Marceline_QUOTE",
    "LeaderVFX": "Leader_Dwarf_VFX"
  },
  {
    "ID": "Leader_PeppermintButler_Pwr",
    "Name": "Powered Peppermint Butler",
    "HPMod": "1",
    "LeaderAbility": "LDR_Draw_1",
    "APThreshold": "15",
    "ActionCard1": "Leader_PeppermintButlerPwr_01",
    "ActionCard2": "Leader_PeppermintButlerPwr_02",
    "ActionCard3": "Leader_PeppermintButlerPwr_03",
    "ActionCard4": "Leader_PeppermintButlerPwr_04",
    "ActionCard5": "Leader_PeppermintButlerPwr_05",
    "Prefab": "PeppermintButler_Pwr",
    "VO": "PeppermintButler",
    "UseChair": "True",
    "ChairOffsetX": "0",
    "ChairOffsetY": "-2",
    "CharacterOffsetX": "0",
    "CharacterOffsetY": "3",
    "HeightAdjust": "-7",
    "ThoughtBubbleHeightAdjust": "-110",
    "QuestPortraitTexture": "PeppermintButler_Battle_Image",
    "PortraitTexture": "Portrait_PeppermintPwr_Hero",
    "VSScreenBackground": "Backdrop_Dungeon",
    "Playable": "True",
    "BuyCost": "3300",
    "CameraWinAnim": "Cam_Thief_Win",
    "PIPTransformP1": "PIP_Finn_Player",
    "PIPTransformP2": "PIP_Finn_Opp",
    "CardRemoveAnimTime": "15",
    "CardPlayAnimTime": "23",
    "BigCardPlayAnimTime": "36",
    "Age": "300+",
    "Height": "15 candy apples tall",
    "Weight": "27 Units",
    "Species": "Candy Person",
    "Quote": "You dare underestimate Dark Magic?",
    "LeaderVFX": "Leader_Thief_VFX"
  }
]